[{"id":10981,"p":"/vefWBq6xpeMYtF7ROgGfXLdp5Qu.jpg","b":"/je79nIbMhZkbuxbvbRclnJwmHYQ.jpg","t":"空无一物","r":5.775,"y":2003,"rd":"2003-09-09","hs":0.173,"d":0.327,"mt":"movie","o":"\"以下是一个真实的故事。人物是确实存在的，名字也是真实可信的。一切都经过查证。戴维和安德鲁是最好的朋友。从九岁开始，他们就是最好的朋友。安德鲁是个非常神经质的年轻人。他害怕一切东西。戴维是个完全以自我为中心的人，从来不能让事情按他满意的方向发展。他们两个都和别的孩子合不来。不久以后，他们意识到，他们生存的最好机会是团结起来。悲惨的安德鲁在他父母去世后变得更加焦虑，很快的甚至变得害怕离开家门。就像尝试做的其它事情一样，戴维成为摇滚明星的梦想被婉转拒绝。身无分文，也没地方可去，戴维搬去和安德鲁一起住，而安德鲁也非常需要帮助。共同生活的日子，戴维提供基本的生活必需品，安德鲁提供一个好朋友的精神支持。戴维勇敢的走出家门找到了工作，而安德鲁留在家的安全区域内作线上旅游经纪。在和社会进行了一生的斗争后，戴维和安德鲁最后快乐的生活在一起。但难过的是，没有什么是永远的。\""}]