[{"id":29568,"p":"/sr9d1gPHIrCs6MMdKUkZNgqghMO.jpg","b":"/4poxKOjyFeSlgzb60h1Xkhsk5iD.jpg","t":"在希尔维亚城中","r":6.8,"y":2007,"rd":"2007-09-14","hs":0.125,"d":0.203,"mt":"movie","o":"　　兜兜转转，来去匆匆。  　　爱情忽然到来，却又悄然而去。经年回首，多少喜怒哀乐已为晕染，乃至伊人面庞亦不再清晰。或只为一丝留恋，抑或那淡而甜蜜的情怀，故将步伐从奔波劳累中移开，来至这曾留下多少梦幻的城市。浪漫之都，大街小巷，遍寻不见那名为希尔维娅的女孩。  　　你在哪里？可曾记得数载之前的爱恋？"},{"id":473320,"p":"/kUMHHbNTBTvB7twXTibDlwPWE9F.jpg","b":"/p43XCRS8Bvdfk36hl7q8cxLhas9.jpg","t":"乡村摇滚少女","r":7.7,"y":2018,"rd":"2018-10-28","hs":0.187,"d":0.202,"mt":"movie","o":"少女住在山间穷乡，虽然能像猴子般攀树，喜欢和男孩子厮磨，但也跟同龄玩伴一样，有机会便看漫画，拿着发泡胶做的仿结他载歌载舞。她梦想拥有自己的电结他，开始逐块卢比储蓄起来，尽管旁人笑她太疯癫，觉得她还是留在母亲身边卖小食洗洗衣服好一点。有一天，她从旧报纸读到一篇介绍正向思维的文章，令她相信正能量只要够强，就能变出实物。"},{"id":1295064,"p":"/sBulkIdsfX0tR8eX9sCiMUGrX8g.jpg","b":"/3QI1svaflS6kBjXyCou3TkjoRU9.jpg","t":"Nyctophobia","r":6,"y":2024,"rd":"2024-05-30","hs":0.321,"d":0.201,"mt":"movie","o":""},{"id":91913,"p":"/zQ6EzF5s4zEeoUHFVZVCg18bsC3.jpg","b":"/nnIV7gR1QhgPcytfOayMqOldKXP.jpg","t":"火山","r":7,"y":2011,"rd":"2011-09-30","hs":0.138,"d":0.2,"mt":"movie","o":"《火山》是冰岛导演鲁纳.鲁纳森的一部小众文艺片。  汉克斯的确是个让人不愿意接近的糟老头儿，退休前仍不忘惩罚作弊的学生。下班回家的路上，年迈的他穿过一群打篮球的活力少年。他点上一支烟，坐在车上用汽车尾气自杀，最后却又莫名其妙的放弃。  他一个人出海捉鱼，船上莫名其妙的破了个大窟窿。他把浸透的衣服脱在院子里，光着身子穿过儿女们诧异的眼神。他也喜欢发呆，坐在马桶上发呆，然后爬上床拥抱他的安娜宝贝。六十多岁的老头儿，爱得特别用力。  他站在窗前等着上班的安娜回家，看到她进门的时候又赶紧坐在沙发上装作认真看报的样子。安娜说，我想知道你为什么总是这么不高兴。总爱发脾气的他此刻却温柔地摸着安娜的脸。安娜喝着她最爱的比目鱼汤的时候突然倒在了地上。  知道安娜生病的时候，他又坐在马桶上哭了。从医院回来的时候，衣衫不整趴在床上的汉克斯特别孤独。汉尼斯眼睁睁地看着夜晚痛苦呻吟的安娜，他抱着她，像她一样发出呻吟。最后，看不得安娜受苦的他亲自结束了她的生命。  孩子们全部不喜欢坏脾气的他。女儿说，我真希望来看望妈妈的时候他不在家。他们不理解母亲怎么能容忍坏脾气的汉克斯，也不理解汉克斯隐晦的爱。儿子来看望母亲的时候，汉克斯就躲出去修理他的破船。"},{"id":604198,"p":"/1GW9dRhoy7ahG4rIFbZkPPwFae0.jpg","b":"/7843Ecmas8f48gSFfwCMM5XLFWe.jpg","t":"Bad Boy","r":0,"y":2023,"rd":"2023-04-28","hs":0.276,"d":0.199,"mt":"movie","o":""},{"id":13432,"p":"/59LTOSSr0o3RVfGkwyCZlxOtRcw.jpg","b":"/aiBC5TDsSsbDk1zPg9wTS7z1Mxm.jpg","t":"让爱飞翔","r":6.7,"y":2003,"rd":"2003-09-17","hs":0.112,"d":0.199,"mt":"movie","o":"本片通过一个善意谎言的故事，刻画了前苏联格鲁吉亚的三个不同年龄女性的形象。艾达是文科大学生，她和母亲玛丽娜和她的外婆爱卡一起住在一套旧公寓里，在这个紧张的地方，生活中的任何一点小事都会引发家庭争执。只有奥塔的消息——爱卡最疼爱的移民到巴黎的儿子——对大家来说是梦想和希望。"},{"id":15842,"p":"/wr26nFLM7AeV2Zy31hiwvtvmMsD.jpg","b":"/8JB2ermx5Rg7pL8GtzJ8fpvIdwi.jpg","t":"En kærlighedshistorie","r":5.458,"y":2001,"rd":"2001-10-26","hs":0.108,"d":0.199,"mt":"movie","o":""},{"id":49689,"p":"/5Bqeb4K42niGdkMw3RVW8Xp6ND8.jpg","b":"/6ooId7ur2K6YJMpyIC1njs2eTGM.jpg","t":"折翼","r":6.9,"y":2002,"rd":"2002-10-24","hs":0.11,"d":0.198,"mt":"movie","o":""},{"id":61559,"p":"/jKLfNp8U8yuwnXQUgbFufwVZmly.jpg","b":"/98lCeBdxbfaCs0M1MviA1D52MO6.jpg","t":"Sabah","r":5.857,"y":2005,"rd":"2005-06-04","hs":0.117,"d":0.198,"mt":"movie","o":""},{"id":378697,"p":"/iTyUHRwpY0BVelK55EAJU0g9gjD.jpg","b":"/9rt3zcWgSWp4s7wKzXYcQlJleJp.jpg","t":"赫迪","r":6.688,"y":2016,"rd":"2016-03-14","hs":0.165,"d":0.198,"mt":"movie","o":"赫迪（马吉德·马斯图拉 Majd Mastoura 饰）的人生似乎从他出生的那一刻起就已经被确定好了，他所要做的一切，就只是按照母亲为他所铺设的道路一直往前走。长大后，赫迪成为了一名推销员，过着日复一日循规蹈矩的生活，他娶了母亲为他安排的女子为妻，婚姻生活亦十分的平淡。赫迪似乎从来都不曾体会过什么叫做生活的激情。"},{"id":413771,"p":"/bCiLhBpJfqSAfHsjhUItxOZqcsi.jpg","b":"/2nR4WHK5ZzZvn96ZSjhgoRpAnP7.jpg","t":"幸福星期天","r":7.3,"y":2017,"rd":"2017-10-06","hs":0.173,"d":0.197,"mt":"movie","o":""},{"id":460032,"p":"/9jNJm1zEWXMpdhMTOwbGgiQnOpO.jpg","b":"/vR45MiWIGbkZUf5Sezghu7aDqtN.jpg","t":"Pashupati Prasad","r":9.2,"y":2016,"rd":"2016-01-29","hs":0.164,"d":0.195,"mt":"movie","o":""},{"id":156220,"p":"/or255kBLL7GEa4525AW0wPuc9oW.jpg","b":"/rXqgPPqCTFAjvxHZg8PgJmqEUWO.jpg","t":"The Staircase II: The Last Chance","r":7.3,"y":2012,"rd":"2012-11-15","hs":0.14,"d":0.195,"mt":"movie","o":""},{"id":1291243,"p":"/eEKaHeNo1xy8XgMkryCbjpeEMHJ.jpg","b":"/A2cMI715eeBJ59epKsn7IJM014O.jpg","t":"सार्की अपलोड गर्नुहोस्","r":0,"y":2024,"rd":"2024-05-23","hs":0.313,"d":0.195,"mt":"movie","o":""},{"id":177155,"p":"/A6lBbswQy6c1RkmwLg2IXgsE4uu.jpg","b":"/xyELWMr8TAL8NE4yvU8osVCwG1U.jpg","t":"Kod amidže Idriza","r":7.5,"y":2004,"rd":"2004-08-20","hs":0.113,"d":0.195,"mt":"movie","o":""},{"id":81549,"p":"/nUON7yeYx6SGcziMBEXDRxHlsUl.jpg","b":"/wqofv8aHAtJtHqt93DBRgltnmhQ.jpg","t":"Her Şey Çok Güzel Olacak","r":7.459,"y":1998,"rd":"1998-11-27","hs":0.101,"d":0.194,"mt":"movie","o":""},{"id":216867,"p":"/s8kjQh0u3Oa6REFzK79XtX0DEh0.jpg","b":null,"t":"画池","r":7.452,"y":2013,"rd":"2013-03-12","hs":0.144,"d":0.194,"mt":"movie","o":""},{"id":244801,"p":"/Ak1Zqkd0eSzpCKuGWVvTVjOjKAG.jpg","b":"/er1tTzpgkPrHq5G15ZyW2mJDAqq.jpg","t":"52个星期二","r":5.2,"y":2014,"rd":"2014-05-01","hs":0.148,"d":0.194,"mt":"movie","o":"16岁女孩比莉被突如其来的消息搞懵了：一直以来和她最亲密的妈妈决定变性！在妈妈做手术、从女人变男人的这一年，她不得不搬去和爸爸住，而且只有在每周二才能和妈妈见一面。比莉倒数着52个星期的过去，与此同时她与两个男孩女孩也分别相处甚密，16岁正是探索自己性的秘密的年纪啊... ◎QAF"},{"id":817880,"p":"/htreozBvM7R2xSLetDNK2Auevq4.jpg","b":"/igkgaF6ZSFSqivNBCYMyoV6VO7s.jpg","t":"Голата истина за група Жигули","r":7,"y":2021,"rd":"2021-04-16","hs":0.22,"d":0.194,"mt":"movie","o":""},{"id":933233,"p":"/Af5i5giLg64WgwgDKeUNMY2vYEA.jpg","b":"/rY1gLGeZkpXUp0A5IJqNR5n9acD.jpg","t":"ملاقات خصوصی","r":7,"y":2023,"rd":"2023-01-04","hs":0.265,"d":0.191,"mt":"movie","o":""},{"id":1449539,"p":"/me7RIXcNdZqaBpXW4swBKNIN12Z.jpg","b":"/vFkZh28i2UkLFTSnvNbybe90HcX.jpg","t":"RIWAJ","r":0,"y":2025,"rd":"2025-03-07","hs":0.373,"d":0.19,"mt":"movie","o":""},{"id":1736,"p":"/gDyQPCMTMov5DKzOuTXdoZxV4Sw.jpg","b":"/24PjzHMBESqwnOcxItPKiJmDosa.jpg","t":"Shoppen","r":6,"y":2007,"rd":"2007-05-02","hs":0.117,"d":0.189,"mt":"movie","o":""},{"id":836490,"p":"/1ZTvygaE3yMdYnV44pynFIyKtSF.jpg","b":"/rmqzU2hLzO1skeSHFnaykVPQLJU.jpg","t":"রেহানা মরিয়ম নূর","r":7.2,"y":2021,"rd":"2021-07-07","hs":0.215,"d":0.189,"mt":"movie","o":""},{"id":1430515,"p":"/eEUxfKUUYhnobs8HA04s1UByjPu.jpg","b":"/5CQoyy8bd1DSffnmtm1rGRlOcz2.jpg","t":"Mr.ರಾಣಿ","r":0,"y":2025,"rd":"2025-02-07","hs":0.371,"d":0.188,"mt":"movie","o":""},{"id":619239,"p":"/eN9KgQEvzuQtQ015WBCQjEJBuwL.jpg","b":"/gcvhT6V6WB4ubM6wn5BMZWSt6XI.jpg","t":"Dnevnik Diane Budisavljević","r":7.5,"y":2019,"rd":"2019-07-18","hs":0.185,"d":0.188,"mt":"movie","o":""},{"id":46820,"p":"/f187ptaaH4E0SVTIyJ9yoZYj6V4.jpg","b":"/g7wtmLZ5n0etZJ4blB06hdo5oJ0.jpg","t":"Madeinusa","r":6.091,"y":2006,"rd":"2006-01-26","hs":0.114,"d":0.188,"mt":"movie","o":""},{"id":327877,"p":"/o2ufnCTXQmV3ILyp1jbI7lhcbeQ.jpg","b":"/yjvDgbc1TOOzQdLomE7xAC5efHO.jpg","t":"Aşk Filmlerinin Unutulmaz Yönetmeni","r":7.1,"y":1990,"rd":"1990-01-02","hs":0.086,"d":0.187,"mt":"movie","o":""},{"id":342550,"p":"/vWmSLCbntynU6ynbWNPk3YyCbaK.jpg","b":"/pyZ8lUrmn8MzGVBNet1K019PcAG.jpg","t":"你带着我","r":6.7,"y":2015,"rd":"2015-05-25","hs":0.15,"d":0.186,"mt":"movie","o":"克罗地亚2016年“申奥片”，故事的主人公是Ives、Nataša、Vedran以及他的妻子。四个人，四种不同的命运因为拍摄电视剧《幸福的囚徒》而交织到了一起。"},{"id":1437600,"p":"/2BkeefesG6KrsNGMeqYgYICsVNO.jpg","b":null,"t":"海蒂","r":0,"y":1993,"rd":"1993-07-18","hs":0.089,"d":0.186,"mt":"movie","o":"　　海蒂（Noley Thornton 饰）从小就失去了父母沦为孤儿，被姨妈收养过着寄人篱下的生活。当姨妈再也无暇照顾海蒂之时，海蒂决定冰雪皑皑的阿尔卑斯上，投奔住在那里的爷爷（杰森·罗巴兹 Jason Robards 饰）。  　　海蒂的爷爷是当地著名的怪老头，个性顽固脾气暴躁，独自一人过着离群索居的生活。海蒂的到来给爷爷带来了不少的麻烦，但随着时间的推移，她的热情和善良渐渐感染了爷爷，一老一少之间建立起了温暖而又坚实的亲情。然而，一场意外的发生令海蒂不得不离开爷爷，来到了富家小姐克拉拉（Lexi Randall 饰）家中，做她的玩伴，克拉拉由于生来无法走路而一直过着闷闷不乐的生活，海蒂的到来替她打开了新世界的大门。"},{"id":57389,"p":"/hCgtAYG53uRdvET4O482paUGMuK.jpg","b":"/rCUI25z0DwcMVBMfZ5MOmMWazkG.jpg","t":"四次","r":7.5,"y":2010,"rd":"2010-05-28","hs":0.126,"d":0.186,"mt":"movie","o":"　　这是一个卡拉布里亚岛的小村子，依山傍海，从山麓间，你可以看到远处的伊奥尼亚海。这是一个好似时间停止的地方，这里的石头有权改变事件的发生，而山羊们则会停下来思考天空的由来。  　　这里住着一个已经时日不多的老牧羊人，他病了，他坚信他找到了续命的良药，他从教堂的地板上收集灰尘，每晚就水喝下。  　　在一个羊圈里的一小片黑土地上，一只山羊生下了一只小白山羊，生命最初的不适只持续了一小段时间，它的眼睛立刻便睁开了，它的蹄子已经可以支撑身体的重量。整个村子的生活都被这个新生命的到来而充满了希望。小羊在逐渐成长，它变得强壮起来，开始玩耍。  　　一次疏忽，它独自离开了在休息的羊群抛开，它在厚厚的植被中迷失了方向，直到精疲力尽，在一株雄伟的杉树下歇脚。  　　这棵巨大的树随着山间的微风摇摆。时间流逝，季节快速地更替，这棵巨大的杉树失去了枝叶摇摆的声音，取而代之的，是机械的轰鸣。  　　杉树倒在地上，他被砍倒了，被肢解，它白色的木材被用当地古老的技术转化为木炭。我们最后一次见它，是它随着烟雾和尘埃消逝……  　　如诗般的电影语言讲述了生活和自然的联系，对于一个被遗忘的永恒之地的诠释，揭示了和谐的真谛。这是一部完全没有用到任何特殊效果的科幻电影，将人们带入了一个未知的奇幻世界，讲述了一个由四个生命互相交叠的奇妙故事。"}]