[{"id":807070,"p":"/ymyCTfBTFdtV8EZplCABygImXIA.jpg","b":"/61bIyX4wA7KyXWGHN9DNSBduR6i.jpg","t":"旋涡","r":7.1,"y":2022,"rd":"2022-01-27","hs":0.945,"d":1.002,"mt":"movie","o":"「我已经拍过令人发噱、惊愕或挑逗的电影。这次，我想让观众跟我一起尽情流泪，体验生命即是电影。」作品总是充满争议的阿根廷名导演加斯帕诺埃，新作《漩涡》一改迷幻癫狂的影像风格，反将镜头转向逐渐萎缩的生命。影片请出意大利恐怖名导达里奥阿基多挑梁主演，面对年迈妻子精神退化、日渐失语，他们习以为常的生活也即将瓦解。影片以分割画面手法，平行呈现这对老夫妇走向凋零的样貌，透过近乎纪录片的拍摄手法，捕捉生命里真实动人的痕迹。"},{"id":980996,"p":"/8Gu30dMoeLhz7fulx1uohyIOlqT.jpg","b":"/aJe7h5SFmyGyJL6WvyFYM6pYBik.jpg","t":"我就愛電影","r":7.1,"y":2023,"rd":"2023-03-10","hs":1.187,"d":1.185,"mt":"movie","o":"2003 年，加拿大安大略郊區。高中生勞倫斯愛電影成癡，奉《戀愛雞尾酒》為畢生經典。他雄心壯志打算去紐約唸電影名校，為賺取學費到錄影帶店打工，卻不屑和客人推銷膚淺電影，只熱衷推薦庫柏力克與保羅湯瑪斯安德森。隨著學校錄取結果一一揭曉，殘酷現實接連向勞倫斯襲來，他才發現自己成了世界上最爛的人！"},{"id":32406,"p":"/nT6RQLoVW5yIlE308e16hl0B4jG.jpg","b":"/c1msGIqjHNZOGFtMXJXVQqdz23F.jpg","t":"如果还有明天","r":7.1,"y":2010,"rd":"2010-08-16","hs":2.566,"d":31.48,"mt":"tv","o":"一位居住在城郊的老师被诊断患有黑色素瘤。在有限的时间里，她要完成自己的心愿，照顾任性的丈夫，关爱成长中的孩子，安抚自己的弟弟却不愿放弃任何一丝的生命精彩。疾病使她从一人独扛到全家齐心支持，病情怎能敌过亲情，爱情和友情。"},{"id":913991,"p":"/lCAss3MZmQydfUF6hnhhghs0YYc.jpg","b":"/pZkhtaqZzcTSz2e5GxUj3CM6jz6.jpg","t":"驚獄77","r":7.1,"y":2022,"rd":"2022-09-23","hs":1.045,"d":1.156,"mt":"movie","o":"取材自真實事蹟，1977年，西班牙正值民主轉型期，社會氛圍動盪不安；一名年輕的會計師因挪用公款被判處20年徒刑，當他在獄中等待審判結果的期間，他與一名老年囚犯合夥，暗中策劃著如何逃獄；究竟他們能否突破重圍，逃出生天？"},{"id":33155,"p":"/m0lZo55EY4Mxf5MdkYoVoIkOR8W.jpg","b":"/7yEbqUxa0UcWCQ0LsIHLnPLO98C.jpg","t":"Offspring","r":7.1,"y":2010,"rd":"2010-08-22","hs":3.178,"d":73.79,"mt":"tv","o":""},{"id":1041054,"p":"/zzMpU0jMaN1UI02TUGvOgi6BMlt.jpg","b":"/CuBCTDsdAEsVbZPrI16kzUlTIV.jpg","t":"为爱杀杀杀","r":7.1,"y":2022,"rd":"2022-12-02","hs":0.737,"d":0.721,"mt":"movie","o":"在这部浪漫的惊悚片中，爱情和迷恋之间的界限变得模糊不清，充满了未知的曲折和极速的变化……"},{"id":858485,"p":"/jIsKmkxMzdCZ0Ux1GVSnu8m6Na6.jpg","b":"/kXElm7wt2kAXEVwJqW4cFhP43nW.jpg","t":"坎特拉","r":7.1,"y":2022,"rd":"2022-09-30","hs":2.588,"d":5.711,"mt":"movie","o":"印度式好莱坞电影。他的男主是好莱坞式的英雄，武功高强，侠肝义胆，拯救村民于水火，是全村的希望。 电影情节很简单，呈现三角形型结构：以shiva为首的村民，以警察为主的部队，以及地主帮派。编剧用障眼法将冲突聚焦在村民和警察之间，之后莫名其妙地让地主杀了祭祀，从而引发村民和地主的直接矛盾，此时村民警察之间的矛盾瞬间瓦解，比一家人都亲。其中shiva受神启，成为了祭祀。这样的情节，其故事结构之简单，塑造英雄速度之高，真的很好莱坞。"},{"id":874194,"p":"/nXnDMbSCKWQfH8WDkEc5kTbXZX8.jpg","b":"/lm96cKoFkmwZUSZnfDLtya05POr.jpg","t":"My Christmas Family Tree","r":7.1,"y":2021,"rd":"2021-11-13","hs":0.669,"d":0.715,"mt":"movie","o":""},{"id":157732,"p":"/94OpFcIZ3ZExqyJgrYafo41tZSt.jpg","b":"/KwKRSJ1bSES8hORdQQn34QwH3V.jpg","t":"执法者：巴斯·里夫斯","r":7.1,"y":2023,"rd":"2023-11-05","hs":4.267,"d":15.564,"mt":"tv","o":"这部剧是关于传奇执法者巴斯·里维斯，美国历史上最伟大的英雄开拓者之一，也是密西西比河以西第一位黑人副法警的故事。"},{"id":936362,"p":"/uX7Vlt9QfZzLYs08Dn8Gw2vUqOE.jpg","b":"/oXbwVZa9oq7N7cD1SgeXccLTU9h.jpg","t":"教官与士兵","r":7.1,"y":2022,"rd":"2022-10-28","hs":0.862,"d":0.886,"mt":"movie","o":"本片基于真实故事改编。Eismayer中尉是奥地利军队里最令人害怕的教官和模范的大男子主义者，但他私下里其实却是个同性恋。当他爱上了一个年轻的、公开出柜的同性恋士兵的时候，他的世界发生了翻天覆地的变化。"},{"id":43924,"p":"/aIHiKAWoGmleP6ODNfQOOCaMeix.jpg","b":"/crFhLNVDCpW6NkU0CmBm3eLq2HT.jpg","t":"橄榄球星之死","r":7.1,"y":2010,"rd":"2010-08-22","hs":0.262,"d":0.426,"mt":"movie","o":"影片以纪录片的手法纪录了美国著名职业橄榄球球星帕特·蒂尔曼（Pat Tillman）离开橄榄球界后从军直到死亡的过程，帕特·蒂尔曼原本是美国家喻户晓的球星，身价百万。但自“9·11”发生后，他毅然抛下了百万美元酬劳转而入伍。但胜利女神并没有眷顾他，2004年4月他在阿富汗的一次追捕行动中身亡，但事后的调查却表明事情远不像想象的那么简单，其实他是被“自己人”误杀身亡，而军方俨然掩盖了这个事实·....."},{"id":950071,"p":"/oaUOV9VCNM5MjrmonqgH4o3XNwQ.jpg","b":"/eF8XLbbBd5cIfvS00tzl0jWAcOX.jpg","t":"嫌疑人X的献身","r":7.1,"y":2023,"rd":"2023-09-21","hs":1.713,"d":2.087,"mt":"movie","o":"一位单身母亲被卷入罪案调查，她的天才数学教师邻居伸出援手，而一名执着的警察也开始深入调查此案。"},{"id":1049638,"p":"/y8L3TEi6fq91O9E8VNGtcq12Ade.jpg","b":"/3di4noZGr04O2lyqgDgWNbyW1wA.jpg","t":"分手有缘人","r":7.1,"y":2023,"rd":"2023-03-17","hs":1.621,"d":1.903,"mt":"movie","o":"由新晋导演雷恩·艾伦·米勒执导的《分手有缘人》是一部爱情喜剧，大卫·琼森和维维安·奥帕拉分别饰演多姆和雅诗。这两个20多岁的年轻人都经历了惨痛的分手，他们在伦敦南部一次展会上相遇。两人帮助对方面对噩梦般的前任，这或许能恢复他们对爱情的信心。"},{"id":51241,"p":"/o8N7viI7hLsirFWotcvxRgujm22.jpg","b":"/4LyTGloPZZx7i1gSSn7ZCxrgW9v.jpg","t":"幻想之爱","r":7.1,"y":2010,"rd":"2010-09-29","hs":0.548,"d":1.093,"mt":"movie","o":"Francis（泽维尔·多兰 Xavier Dolan 饰）和Marie（莫妮亚·乔柯里 Monia Chokri 饰）是一对默契十足的异性好朋友。在一次晚宴上，他们碰到了刚来到这座城市的乡村男孩 Nicolas（尼尔斯·施内德 Niels Schneider 饰）。随着和这个漂亮的男孩的进一步交往，这两个平日亲密无间的好朋友却发现周遭的种种莫名发生了改变，似乎有一种新的情绪影响着彼此。不久，Francis和Marie发现自己都不知不觉地爱上了这个不可捉摸的少年Nicolas，而两个人昔日坚不可摧的友情也第一次面临着挑战。爱情和友情，到底哪一个才是他们真正的归宿呢？"},{"id":1074673,"p":"/bnxW2Pb0k2n7G7atvBs7wnwaCdE.jpg","b":"/pni27Qk251zHWwtZwcxxFPE5ErI.jpg","t":"இறுகப்பற்று","r":7.1,"y":2023,"rd":"2023-10-06","hs":0.932,"d":0.848,"mt":"movie","o":""},{"id":32415,"p":"/niXtnEK5JRJ1YMkIqvaVAVDJrRd.jpg","b":"/2Ib8kvWa9gGhJrAfGlhIvbmtbWn.jpg","t":"柯南秀","r":7.1,"y":2010,"rd":"2010-11-08","hs":4.288,"d":332.552,"mt":"tv","o":"柯南·奥布莱恩和他的搭档安迪·里希特讨论当前的新闻话题，采访名人和名人。"},{"id":153742,"p":"/jaQq8yngDA1pnMRcFcxfq6Hhrop.jpg","b":"/cTCZNEM6tXeyCotgsYlVw5lT1tF.jpg","t":"We Need to Talk About Cosby","r":7.1,"y":2022,"rd":"2022-01-30","hs":2.956,"d":7.818,"mt":"tv","o":""},{"id":128158,"p":"/aiNCnE2FOvBXlTMCmILnIC78QgM.jpg","b":"/eUBljjyOlY3Tlq1DBU2TFbela0w.jpg","t":"忍石","r":7.1,"y":2013,"rd":"2013-02-20","hs":0.581,"d":1.044,"mt":"movie","o":"在阿富汗或者是别的什么正在遭受战火的村庄，一个漂亮的中年女人在起居室日复一日照顾着她孱弱的丈夫，一天，绝望的女人爆发了，面对她沉默的丈夫，滔滔不绝地谈到孩子、孤独、梦想、欲望……她抚摸他，亲吻他，那些尽管结婚十年了她却从来没有做过的事情。这个瘫痪多年的男人无意中成了寓言中的那块具有神奇魔力的忍石：倾听和吸收所有的痛苦与秘密。在等待丈夫苏醒的日子里，女人也在顽强地生活着。她在唯一理解她的亲人姑姑那里寻求庇护，同时也在对一个年轻军人萌生的爱情中，重新发现了自己。"},{"id":38294,"p":"/bJQnuGaXML31QyjxwMXuu39Tye1.jpg","b":"/lvfoHcP233tfmqJz3MRIdKDbyQl.jpg","t":"Life's Too Short","r":7.1,"y":2011,"rd":"2011-11-10","hs":1.285,"d":4.425,"mt":"tv","o":""},{"id":35370,"p":"/3cdA7fxfupmca60gkg29osDdek0.jpg","b":"/blal5XDKs2nKU8zcWNZrYnb4XkO.jpg","t":"特效化妆师大对决","r":7.1,"y":2011,"rd":"2011-01-26","hs":2.745,"d":36.114,"mt":"tv","o":"Syfy真人秀节目《Face off》于2011年1月26日首播。参赛者将比拼特效化妆技术。评委是世界顶尖的影视特效设计师和化妆室，参与制作的项目包括《吸血鬼猎人巴菲》、《黑夜传说》、《生化危机3：劫后余生》、《X档案》和《剪刀手爱德华》等。"},{"id":51157,"p":"/xEd80BZu4YcpB3o2CAX23Se6lto.jpg","b":"/oqDrZKXGoMZl8HrSENtGP4f29HF.jpg","t":"חטופים","r":7.1,"y":2010,"rd":"2010-03-06","hs":1.672,"d":8.678,"mt":"tv","o":""},{"id":59490,"p":"/7qBfQ2x3FnbB7uRaHQOBjfWFBpc.jpg","b":"/owK8qNJq4nUDjgnCXi714kk2TtL.jpg","t":"忘梦洞","r":7.1,"y":2010,"rd":"2010-11-03","hs":0.575,"d":1.178,"mt":"movie","o":"　　法国南部的Chauvet岩洞里，有三万年前的原始壁画，还有冰河时期的哺乳动物化石，但洞口一直被落石封住，直到1994年被科学家偶然发现。这个宝贵的洞穴被严密保护着，赫尔佐格只获准进洞拍摄六天，每天四小时，他还采访了相关研究的科学家们，用他特有的方式，探索史前人类对事物的认知和表达方式、艺术和文明史的诞生、以及现今围绕在洞穴四周的好奇人群。他还注意到现代工业对史前遗迹的侵蚀——Chauvet岩洞附近恰有一个核电站，已经因为温水汇流形成生态圈，里面连鳄鱼都有了，Chauvet未来可能受到被淹没的威胁。  　　这是沃纳·赫尔佐格首次用3D形式拍摄他最热衷的纪录片。 ©豆瓣"},{"id":355254,"p":"/uYYxSGwKWrnN86Uyuk0NyDzCLwh.jpg","b":"/grVKCMGxeQlungQskzxEWQq8VE9.jpg","t":"德·帕尔玛","r":7.1,"y":2016,"rd":"2016-06-10","hs":0.365,"d":0.489,"mt":"movie","o":"电影制作人之间的亲密对话，记录了德-帕尔玛 55 年的职业生涯、他的生活和他的电影制作过程，其中包括揭示性的轶事，当然还有大量的电影片段。"},{"id":155649,"p":"/bnnWdGffhZjKbKx1Z6HWtR4JKBx.jpg","b":"/64n3Rha8hN0i0UBcRrN3l60UFC.jpg","t":"Crushed","r":7.1,"y":2022,"rd":"2022-01-12","hs":2.687,"d":6.237,"mt":"tv","o":""},{"id":477428,"p":"/qWruoYDOTVXuxcAIpHmnVLFSJhq.jpg","b":"/rDswI6jJKQV0BcRUBfcg26OmIbX.jpg","t":"被涂污的鸟","r":7.1,"y":2019,"rd":"2019-09-12","hs":1.027,"d":1.598,"mt":"movie","o":"该片改编自作家杰西·科辛斯基撰写的同名处女作，原著围绕一个无名小男孩在东欧农村躲避战火的经历展开，故事从社会、历史等不同角度，反思与理解边缘人物的荒诞行为。"},{"id":40290,"p":"/42gO1qCC6GPtHKNXvOdhunhzyS3.jpg","b":"/kxb02OCWt9VYMvVeoY7dNhSNFT2.jpg","t":"廚神當道","r":7.1,"y":2010,"rd":"2010-07-27","hs":3.103,"d":65.867,"mt":"tv","o":"美国FOX频道推出规模最大，甚至于全美最大，参赛者阵容最庞大的厨艺竞赛综艺节目，全美厨师选秀活动。 参赛者几乎来自各行各业，相同的是他们都对烹饪充满热情与希望！而最后的胜者不仅仅可以获得二十五万美元，属于你自己的菜谱，还有一个最重要的东西，Masterchef的奖杯。"},{"id":79897,"p":"/6H3DSfcg0LKDZHiDRC8oaF15WeO.jpg","b":"/mekK9e3Qh3cvEuosDtUjkMm5z6t.jpg","t":"പ്രാഞ്ചിയേട്ടൻ & The Saint","r":7.1,"y":2010,"rd":"2010-09-10","hs":0.36,"d":0.631,"mt":"movie","o":""},{"id":202102,"p":"/wAoei8KMQ5SXpmABw43hbfQKS8q.jpg","b":"/hGjTV2L4WHJ3HfM3r33GdFVPz6d.jpg","t":"时空怪客","r":7.1,"y":2022,"rd":"2022-09-19","hs":4.684,"d":30.327,"mt":"tv","o":"本剧发生在老版《时空怪客》的科学家山姆·贝奇进行时空跳跃并失踪的30年后。故事围绕另一位科学家班恩·宋展开，他受命领导一个新的团队重启时空跃进项目，以揭开原始实验和失踪科学家的神秘面纱。"},{"id":73448,"p":"/m8qpq78icrD5BKjylb2iYwoydKb.jpg","b":"/xYlTXk9aYoL7U0lVjzf3fUGmJMC.jpg","t":"迪赫奇","r":7.1,"y":2011,"rd":"2011-08-25","hs":0.317,"d":0.519,"mt":"movie","o":""},{"id":32200,"p":"/qAP6gXpwwIWwJeoSHpKAMhHYVqF.jpg","b":"/24Kr67DhRIDalcRvarQeQ9650RI.jpg","t":"犯罪心理：嫌犯動機","r":7.1,"y":2011,"rd":"2011-02-16","hs":1.974,"d":12.432,"mt":"tv","o":"美国联邦调查局（FBI）犯罪行为分析组内有一支特别行动组，这支特别行动精英小组通过使用非常规的调查方法和非常激烈的手段，来抓捕美国最邪恶的罪犯。作为处长的特别探员Sam Cooper拥有生俱来的领导气质，具有极大的热诚。为了坚持自己的信仰，他不惜冒着丢掉饭碗的危险。Cooper奋力地去避开政治上的官僚主义并亲自遴选了一组风格各异的分析员工作于Quantico的限制之外。这些分析员包括：意志坚强、勇于直言的Beth Griffith，他是队伍中的新兵，刚从联邦调查局的威胁评估任务组中调来加入他们的；前英国特种兵Mick Rawson自信、英俊，他是技术高超的神枪手并拥有一双看清事物的双眼，要将一切罪恶斩草除根；John “Prophet” Sims曾经是一个罪犯并带有一点街头小智慧，他有冷静、东方禅师般的外表，并决心为过去的失误赎罪；Gina LaSalle是一个迷人、坚强的探员，具有敏锐的洞察力；Penelope Garcia是一个电脑狂，过去的几年里他力助Hotchner探员和BAU团队处理最棘手的案子。这群卓越的联邦调查局探员信仰坚定，他们坚持不懈地完成任务，把国家最危险的罪犯送到审判庭。"}]