[{"id":113965,"p":"/oCs9z30bHiYknu4S2vuTTdmSSBN.jpg","b":"/xZDyOXQckDmTWIXJ9cuDSH8ZazD.jpg","t":"前辈，请不要涂那支口红","r":7.3,"y":2021,"rd":"2021-01-18","hs":2.817,"d":8.662,"mt":"tv","o":"改编自2017年公开后人气飙升的同名网络小说。讲述了可爱的女前辈，和性感、真挚的直进男后辈之间的“蜜糖”罗曼史。"},{"id":123084,"p":"/bsMOr1rfG0Vk5sneiWQVegYHfSv.jpg","b":"/qOpZpZ0msugCtq1XHYycvGVEnk.jpg","t":"主宰世界","r":6.8,"y":2021,"rd":"2021-05-16","hs":2.81,"d":8.661,"mt":"tv","o":"　　一群黑人妇女在哈林区工作、生活和玩耍，为统治世界而奋斗的故事。他们不仅在生存，而且在一起茁壮成长。"},{"id":107314,"p":"/4k4weoS5xQsUiEfsEPWlfhtmZKW.jpg","b":"/sVb1PFoa5KnMoO7SiLMxgGvXPHs.jpg","t":"百战天虫","r":5.7,"y":2021,"rd":"2021-12-16","hs":2.786,"d":8.585,"mt":"tv","o":"　　美国终极英雄、超级爱国者麦格鲁伯在狱中腐朽了十多年后终于获释。他的任务：从他过去的准将指挥官伊诺斯·奎斯手中干掉一个神秘的恶棍。在整个世界都处于众目睽睽之下的情况下，麦克格鲁伯必须重新组建他的老团队，以击败邪恶势力。"},{"id":122978,"p":"/eJtciFQoFjxPXLlvNjSl4ezi6Gz.jpg","b":"/nZ9rzh0JRESVR63W5MCWl36Txci.jpg","t":"所以我和黑粉结婚了","r":7.481,"y":2021,"rd":"2021-04-30","hs":2.804,"d":8.521,"mt":"tv","o":"该剧翻拍自同名小说，讲述从乡巴佬摇身一变为大明星的男人和变成他官方黑粉的杂志社女记者之间的爱情故事，小说曾翻译成多国语种出版，2016年曾翻拍成同名中国电影。崔泰俊将在片中饰演宇宙大明星后俊，虽然外表高冷，但其实内心深藏着初恋的痛楚，因机缘巧合与崔秀英所饰演的黑粉、杂志社的李瑾莹开始了同居生活，展开了一段紧张刺激的爱情故事。"},{"id":93736,"p":"/wIKQRtc2kKiBmBnkOjjvMqIDfah.jpg","b":"/ooq4qnr6ZCcc7ziJMOw6LTtMyoO.jpg","t":"武士时代：为统一日本而战","r":7.1,"y":2021,"rd":"2021-02-24","hs":2.803,"d":8.513,"mt":"tv","o":"本剧通过动态场景重现与专家评述，再现了16 世纪封建时期的日本在混战之下的动荡历史和权力斗争 。"},{"id":122486,"p":"/vL4O0WQG4P4O8MpbmIRrVUFNMGC.jpg","b":"/zc0mxafWd2q99E5UCXcyXNn6U7M.jpg","t":"鸟姑娘","r":5.9,"y":2021,"rd":"2021-04-05","hs":2.775,"d":8.434,"mt":"tv","o":""},{"id":116175,"p":"/c1CB1K9aPQ2F7zNNSfR94xvJfSC.jpg","b":"/4zXfxbN56cqhmNqZl6956zfVs5E.jpg","t":"我们挚爱的故事","r":7.8,"y":2021,"rd":"2021-01-08","hs":2.792,"d":8.423,"mt":"tv","o":"一直被人压是什么感觉？周书逸瞪着手中的全班成绩单，又一次看见高仕德的名字压在自己头上， 他就不明白了，自从小学五年级这人走进自己的生命后，第一名就离他远去，他从「永远第一」变成「万年老二」…… 终于，忍到高三他不必再忍。周书逸窃笑，很好，一进大学分道扬镳，他们终于可以再也不见！满心愉悦迎接大学生活的他再度加入自己锺爱的游泳社，一路被捧着，没想到毕业前迎新生入社传承PK赛上竟然看见高仕德出现！这次，不仅来不及在暗恋的学姐面前帅气夺冠，还掉进水里抽筋差点溺水，周书逸只有三个字…好-想-死! 之后发现学姐和自己最好的朋友交往，他更想撞豆腐自杀，果然遇上高仕德就是没好事！他不知道天地那么大，为何到哪高仕德总跟着他。那个人说...「我一直看着你」，是要看到什么时候才肯放过他？"},{"id":135805,"p":"/vMzhxAdiDr5267BuM8GXi1yt8jv.jpg","b":"/4ndun7pyZyHuokSWj7SCkp3j8E6.jpg","t":"Tuttle Twins","r":8.625,"y":2021,"rd":"2021-10-13","hs":2.785,"d":8.41,"mt":"tv","o":""},{"id":124601,"p":"/evcZ0HndXg7SDpuWMHtSj1YFiaj.jpg","b":"/sCY4N87OYPe3UAMdpnODCb1STup.jpg","t":"Hvide Sande","r":6.111,"y":2021,"rd":"2021-05-03","hs":2.775,"d":8.384,"mt":"tv","o":""},{"id":117896,"p":"/si2mpj75SD4PMlT65sk58r4aOvi.jpg","b":"/fY7wigRHMritnQiX47wgCEMau5G.jpg","t":"红天机","r":7.3,"y":2021,"rd":"2021-08-30","hs":2.774,"d":8.336,"mt":"tv","o":"讲述了史料记录极少的一位朝鲜时期的女性画家的故事，加上郑作家天马行空的想象力，形成了一部奇幻浪漫史剧。故事会围绕进入景福宫的绝世美女画工红天机、失明后依然能识别星座和天象的观星监河澜以及以俊美而闻名的风流公子安平大君展开。"},{"id":98187,"p":"/qN6HCKR3ZRqbpGBWFctVlSTKR2k.jpg","b":"/4sIjlFa2jn0SsWQVuTBEFgQy4eH.jpg","t":"贝克街游击队","r":7.217,"y":2021,"rd":"2021-03-26","hs":2.786,"d":8.3,"mt":"tv","o":"该剧集以维多利亚时代的伦敦为背景，讲述了一群陷入困境的街头少年被人操纵，为阴险的华生医生及其神秘的商业伙伴（难以捉摸的夏洛克·福尔摩斯）破案的故事。犯罪活动逐渐呈现出令人恐惧的超自然背景，并且出现了一股黑暗势力，这支非正规侦缉小队的成员必须团结起来，一起拯救伦敦和整个世界。"},{"id":116045,"p":"/eJomyEtQE9WF2GZWXcfzj3Omb5Q.jpg","b":"/ollH7DfG9E0iEX9MsnuGtZYFmvQ.jpg","t":"哈啰，我好吗？","r":7.43,"y":2021,"rd":"2021-02-17","hs":2.778,"d":8.295,"mt":"tv","o":"　　一事无成、生活惨淡的女子深信她已失去所有热情，直到年轻且朝气蓬勃的自己有天出现在眼前，要她做出改变。"},{"id":129035,"p":"/6stEKYqgLBhSieTRnnZ5ShE5ZPS.jpg","b":"/mFAiusk8yF0GeBK0xIcte4GdWWE.jpg","t":"行尸走肉：起源","r":7.8,"y":2021,"rd":"2021-07-15","hs":2.836,"d":8.125,"mt":"tv","o":"《行尸走肉：起源》是一系列特辑，探索该系列最著名角色的旅程。 每一集都从一个角色的角度描绘了僵尸启示录的故事，并以描绘这些标志性角色的演员的新采访和叙述为特色，并与他们迄今为止旅程中最关键时刻的剪辑交织在一起。"},{"id":126829,"p":"/xIyV8VjF9ZRnI0w2MFJfSxev3q7.jpg","b":"/3AHNZZavCu1ynTOPI4QVUmhFVus.jpg","t":"萨蒂亚吉特·雷伊：大师短篇故事精选","r":6.3,"y":2021,"rd":"2021-06-25","hs":2.726,"d":8.047,"mt":"tv","o":"　　从讽刺到心理惊悚片，著名导演和作家萨蒂亚吉特·雷的四个短篇小说被改编为这一系列的银幕。"},{"id":93808,"p":"/ewEgxHvSJnQxH4nwYUr8yajqHOQ.jpg","b":"/1bztL5ZgA9m8OSxO51TBYyoVO8P.jpg","t":"欧罗巴部落","r":7.029,"y":2021,"rd":"2021-02-19","hs":2.729,"d":8,"mt":"tv","o":"　　故事讲述2074年，一场神秘的全球性灾难后，欧洲大陆解体为林立小国。各个“部落”为争夺大陆的统治权而相互争斗。三个兄弟姐妹凯诺、丽芙、伊利亚为了改变这片新的“欧罗巴”大陆的命运，他们被迫踏上征途。"},{"id":123725,"p":"/jRQA9OTdIm28B9hwJ2cj4Dnp6Rt.jpg","b":"/qFmfR1BQok2tQSlnqzya8yGKfgK.jpg","t":"Yeşilçam","r":7.636,"y":2021,"rd":"2021-04-22","hs":2.722,"d":7.96,"mt":"tv","o":""},{"id":137635,"p":"/tYBLQeB44JRx2UlUpQjBnSpVzN.jpg","b":"/yvb8rJRXLiYF6QtU0jdPO7kJrVS.jpg","t":"模范审判","r":6.9,"y":2021,"rd":"2021-10-31","hs":2.716,"d":7.941,"mt":"tv","o":"一场席卷全国的审判不时开始，将受害者和被告——以及他们的家人——置于媒体风暴的中心。 作秀公审着眼于这样的一个案例，一位富有企业家的傲慢女儿塔莉莎·坎贝尔 (Talitha Campbell) 在同学汉娜·埃利斯 (Hannah Ellis) 失踪后被捕，她是一位单身母亲的勤奋女儿。 从塔莉莎被捕到陪审团的最终裁决，作秀公审在法律战的双方之间切换，辩护和检方为他们对汉娜真实遭遇的版本以及关于 Talitha 的真相而斗争：被诬告？ 还是冷酷无情的凶手？"},{"id":118321,"p":"/jXC3tk2apwPxDpFHQaQH5ATDhlP.jpg","b":"/ijnwlEQtrPih5VJo0dt3IXcB4kN.jpg","t":"艾伦对决法罗","r":6.5,"y":2021,"rd":"2021-02-21","hs":2.704,"d":7.894,"mt":"tv","o":"　　讲述伍迪·艾伦、米亚·法罗及两人组建的家庭背后的故事，深究两人关系背后的丑闻，包括伍迪·艾伦被指控性侵以及家庭影像片段、法庭文件、警方证据和此前未曝光的录音内容等"},{"id":116500,"p":"/biaVLydNo4NQx90j7IAFlOiePub.jpg","b":"/2B9d0FHqNGPBIDX9aQ265fCVzmO.jpg","t":"彭布罗克郡谋杀案","r":6.7,"y":2021,"rd":"2021-01-11","hs":2.702,"d":7.888,"mt":"tv","o":"　　本剧根据高级调查官史蒂夫·威尔金斯与ITV新闻记者乔纳森·希尔共同撰写的纪实文学改编，讲述了1980年代有两起未解决的双重谋杀案。2006年，新上任的督察长史蒂夫·威尔金斯(卢克·伊万斯饰)决定再度调查这两起案件，采用了现代法医调查方法，利用DNA等线索，将两起谋杀案与一系列的盗窃案联系在一起。在这些盗窃者即将刑满释放前，史蒂夫团队能否找到足够的证据来指控嫌犯呢？"},{"id":104712,"p":"/6XxC7cnwRxBQ0wgb2oUdHb0XO23.jpg","b":"/glc3cG3Sx0uRDCTxYl7kY1SqofD.jpg","t":"苏格兰裙男子：与萨姆和格拉汉姆同行","r":7.7,"y":2021,"rd":"2021-02-14","hs":2.713,"d":7.875,"mt":"tv","o":"该节目中，Heughan和McTavish将带大家来一场充满欢乐的苏格兰旅行。《古战场传奇》后，两人再次相聚踏上史诗般的冒险旅程，探索他们的文化遗产，与一群了不起的人会面，他们将真正展示何为苏格兰人。"},{"id":5768,"p":"/fSWXCeTS80yR1vHTLVRRagyQmjQ.jpg","b":"/sfOqq7YR75DOdUS3SbaK9fkmO01.jpg","t":"天堂城","r":8.055,"y":2021,"rd":"2021-03-25","hs":2.747,"d":7.786,"mt":"tv","o":"布鲁斯·威利斯、约翰·特拉沃尔塔将领衔主演动作新片[天堂城](Paradise City，暂译)，泰国演员普莱亚·伦德伯格(Praya Lundberg)担任女主角。该片由查克·拉塞尔([变相怪杰])执导，科里·拉奇([外星罪孽])、艾德·约翰共同操刀剧本。该片讲述叛逆的赏金猎人瑞安·斯旺(威利斯饰)必须在夏威夷的犯罪世界中开辟自己的道路，并向杀害他父亲的头目(特拉沃尔塔饰)复仇。"},{"id":104157,"p":"/49NGm94x1suwVkAc08mhYnJcbEH.jpg","b":"/wPJgjOfsFUny1WBo53Q9xtIMSs.jpg","t":"卡特拉之迷","r":6.993,"y":2021,"rd":"2021-06-17","hs":2.687,"d":7.723,"mt":"tv","o":"一座冰下火山爆发。一年过后，融冰释放出史前时期的神秘元素，引发了无法意料的后果。"},{"id":90702,"p":"/dzAwoFc87V2zku5FqYoijKfCOvh.jpg","b":"/4J713WSLvfKFp7ZiZQopB7vXtNN.jpg","t":"郊狼","r":7.8,"y":2021,"rd":"2021-01-07","hs":2.704,"d":7.694,"mt":"tv","o":"　　这部6集剧之前Paramount Network开发。由David Graziano、Michael Carnes及Josh Gilbert执笔的剧集《郊狼》聚焦在美墨边境，讲述当了32年美国边防警卫队探员的Ben Clemens（Michael Chiklis饰）过去一直为美国抓捕墨西哥偷渡者。现在他被迫为对面的人效劳，但当主角正式待在边境的另一边后，他发现自己非黑即白的观点，以及原本的忠诚都被慢慢动摇起来。"},{"id":133439,"p":"/jDhM8gMmzOMxmg8FC0VEf2DMaNb.jpg","b":"/bErOVyokqltl1on0t1GYVeKNYkI.jpg","t":"月光镇","r":6.1,"y":2021,"rd":"2021-09-14","hs":2.67,"d":7.659,"mt":"tv","o":"芬利·卡伦家族是一个由同父异母的成年兄弟姐妹组成的功能失调家庭，他们正在争夺家族企业的控制权。这是新斯科舍省南岸一个摇摇欲坠的避暑胜地，离破产还有一个化粪池，其核心是一个黑暗的家庭秘密。"},{"id":119337,"p":"/2wAf6bzCDke3bO33429XCPMZRN2.jpg","b":"/aMDAchE1OFyQ50gylIhPkyxZyk6.jpg","t":"摩门教徒谋杀案","r":7,"y":2021,"rd":"2021-03-03","hs":2.673,"d":7.629,"mt":"tv","o":"剧集以前所未有的全面角度，回顾摩门社群内最令人惊骇的罪案，审视背后的犯罪首脑。剧集细探盐湖城发生的三起炸弹爆炸案，罪案导致两人死亡，盐湖城人心惶惶。第三名受害者马克·霍夫曼是一位知名收藏家，专门收藏珍稀的古籍文献，包括不甚光彩的《蝾螈手札》，内容足以撼动摩门教的根基。这几起谋杀案件冲击了摩门教的核心，加上调查人员在霍夫曼车上发现众多毁损的早期摩门手札与日记，使得整个摩门社群掀起轩然大波。霍夫曼在生死关头挣扎，调查人员则加紧脚步，设法查出真相。"},{"id":119180,"p":"/qzutbxi3Ki66Un16KCfZI2vwELk.jpg","b":"/5psyZg3ETZbMpsQD7EjbFXCjQf3.jpg","t":"乡村星愿","r":7.4,"y":2021,"rd":"2021-03-19","hs":2.678,"d":7.599,"mt":"tv","o":"　　怀抱梦想的年轻乡村歌手贝利（凯萨琳·麦菲饰）眼见事业和私生活变调，只好接下新工作，替一个名叫博（埃迪·希布莱恩饰）的粗犷牛仔照顾五个小孩。她这位新手褓姆凭藉迷人的南方气质和愈挫愈勇的性格，从容应对雇主家庭的种种状况，充当他们缺席已久的母亲角色。但她却万万没有想到，这个具有音乐天分的家庭竟让她重圆星梦，组成她梦寐以求的乐团。"},{"id":119284,"p":"/klL9vBIRdEeSLtjhn83pCNcVguZ.jpg","b":"/1kPC5upPbdfh4l42cB824ywT0sq.jpg","t":"真爱基因","r":6.546,"y":2021,"rd":"2021-03-12","hs":2.644,"d":7.558,"mt":"tv","o":"　　一名 DNA 专家发现找到完美另一半的方法，于是创办出大胆又新颖的 DNA 配对服务，爱情与谎言因而如同螺旋般缠绕相生。"},{"id":100962,"p":"/oJOpQYVQJXwUCQRAZuPlx1asy0H.jpg","b":"/isYIHR7fH8TdS0pBFCaHIAHyk3M.jpg","t":"良辰美景好时光","r":7.5,"y":2021,"rd":"2021-04-08","hs":2.666,"d":7.557,"mt":"tv","o":"讲述正能量歌手梁辰和计算机系大数据研究方向的大四学生陆景之间互相砥砺，共同成长的励志故事。“青春须早为，岂能长少年”，梁辰、陆景等人在各自的领域发光发热，用自己的专业精神去鼓舞和指引喜爱自己的人。用音乐表达“至善、至真、至美”的梁辰，致力于将好的音乐作品带给听众。热爱计算机与大数据研究的陆景，通过研究人类各种复杂的行为、心理信息等海量数据获得大数据学术界的高度认可。陆景用其扎实的专业素养，积极正面地影响着身边的同学们，为社会数据研究做出贡献。两个原本遥遥相望的陌生人因为大数据而相遇，在追梦的旅途中不断靠近信任彼此。"},{"id":130364,"p":"/jQZIZcmkSFPL1QEMjQgqXKKFb44.jpg","b":"/yhhStAMdc6Q0iwDlOdqgjN2x5L0.jpg","t":"王国：风起云涌","r":7.4,"y":2021,"rd":"2021-08-13","hs":2.668,"d":7.544,"mt":"tv","o":"在竞选搭档遇刺后，一名宗教领袖成为头号总统候选人。就在他把握这次重大机会的同时，对谋杀案的调查也在进行中。"},{"id":135386,"p":"/mvmlsAfnk22XSJTDkwBoPtUobWt.jpg","b":"/cjwKcuHxxrm2JGT2Y9UpDqZtqwH.jpg","t":"Red Election","r":6.5,"y":2021,"rd":"2021-10-03","hs":2.65,"d":7.485,"mt":"tv","o":""}]