[{"id":11844,"p":"/2TdHo37gBCZFT613VcLMbP5eM65.jpg","b":"/1uf6ybrvTzx1hs64Phr5HOw4T2N.jpg","t":"The Van","r":6.34,"y":1996,"rd":"1996-11-29","hs":0.21,"d":0.473,"mt":"movie","o":""},{"id":127880,"p":"/4CuPUYdqG8YgzSwGWHiSCpXBx4F.jpg","b":"/yZkIWGk7easNUNOag67dqc6irmd.jpg","t":"我的双面童年","r":6.8,"y":2012,"rd":"2012-09-16","hs":0.304,"d":0.473,"mt":"movie","o":""},{"id":38428,"p":"/sFzo2Ss4PQfNUlrzeTfwoVp5ajE.jpg","b":null,"t":"我的父亲甘地","r":5.3,"y":2007,"rd":"2007-08-03","hs":0.263,"d":0.473,"mt":"movie","o":"影片由弗罗兹·阿巴斯·克汉执导，讲述了甘地恪守自己制定的严格的原则，导致与任性儿子哈里拉尔之间的冲突不断。影片通过家庭矛盾，展示了甘地对儿子的冷漠，有时甚至是个很霸道的父亲。展现了他在不顾一切地寻求父爱的儿子和自己公众责任之间的无奈与伤感。影片背景为1906年到1948年(甘地遇刺身亡)间的南非和印度，影片还讲述了哈里拉尔苦闷、酗酒上瘾，还一度皈依了伊斯兰教，反抗自己严厉的父亲。"},{"id":1028537,"p":"/1sYxuse7fhYQ0Zej8Z0tGizD9uu.jpg","b":"/gycBJ7rtVZyfR9ijkhAzNEunleI.jpg","t":"Christmas Class Reunion","r":5.9,"y":2022,"rd":"2022-12-10","hs":0.525,"d":0.473,"mt":"movie","o":""},{"id":421761,"p":"/zArq5FAPcaMPe1xv6b0ZmDEyK9a.jpg","b":"/gqXjcmI4FoQXw1xPNPzVopZ6Sjf.jpg","t":"A Dream of Christmas","r":6.3,"y":2016,"rd":"2016-12-03","hs":0.352,"d":0.473,"mt":"movie","o":""},{"id":107729,"p":"/cDbF8bejKlUe7w2yAZ4Vch0xEKT.jpg","b":"/aE63S5yXWcI3A4vSYCkyhPcUpa4.jpg","t":"The Stranger Beside Me","r":6.531,"y":1995,"rd":"1995-09-17","hs":0.208,"d":0.473,"mt":"movie","o":""},{"id":21372,"p":"/zppNLGxL0ttNhcd36wBXb4JQbYA.jpg","b":"/u44wc4bo3tGziVbPtZDFx9YOkIu.jpg","t":"浮生火热","r":6,"y":2009,"rd":"2009-06-26","hs":0.277,"d":0.472,"mt":"movie","o":""},{"id":630926,"p":"/l9l1v24dqbAlHdYHpt9T84zs17J.jpg","b":"/8pMLz5lWvJFhyXjklwK2X4jEkzZ.jpg","t":"A New Year's Resolution","r":6.2,"y":2021,"rd":"2021-01-09","hs":0.479,"d":0.472,"mt":"movie","o":""},{"id":874230,"p":"/oV5r8NlY2qJbttdoH0kVd3q2AnI.jpg","b":"/9t0NtTrHxNYM2L8xmCLjmiIpAZe.jpg","t":"Time for Them to Come Home for Christmas","r":6.3,"y":2021,"rd":"2021-11-27","hs":0.479,"d":0.472,"mt":"movie","o":""},{"id":126186,"p":"/m01l1KdR9oQiB3pw7uPFQtEEGcX.jpg","b":"/y8CGiAYo2E6Ld82FvNvwRwr8937.jpg","t":"纽约客@上海","r":6.2,"y":2012,"rd":"2012-05-03","hs":0.303,"d":0.472,"mt":"movie","o":"上海，21世纪全球贸易中心。每天都有更多的外籍商人来到上海，渴望了解到中国做生意的方式。这些外国人中有我们的同事，老板，邻居，客户……\r 　　当雄心勃勃的纽约律师山姆（丹尼尔·海尼 Daniel Henney 饰）被意外的派到上海时，他立即陷入了法律泥潭，使他差点丢了工作。但随着一位聪明性感的助理（朱珠 饰），一个机灵的上海记者（耿乐 饰），一位漂亮的迁居专家（伊丽莎·库伯 Eliza Coupe 饰），以及一个人脉广泛的老前辈（比尔·帕克斯顿 Bill Paxton 饰）的帮助，山姆可能有机会保住工作，寻找到爱情，并且学着去欣赏他美好的故乡……"},{"id":258770,"p":"/onGX91lNMsCuXQSNLQaji0xXTXG.jpg","b":"/8FSd4MmW9IegQPdpwJfKHcjBvrk.jpg","t":"في شقة مصر الجديدة","r":6.8,"y":2007,"rd":"2007-03-14","hs":0.263,"d":0.472,"mt":"movie","o":""},{"id":358083,"p":"/ZfRRNNfDdfeTYj8QD4EzIOCSi9.jpg","b":"/5gWhwqXKVXXtzFgxEmnQ7kAh0si.jpg","t":"天堂套房","r":6.481,"y":2015,"rd":"2015-10-29","hs":0.339,"d":0.472,"mt":"movie","o":"影片讲述了五个相互交织的故事。六个角色出现在阿姆斯特丹，他们有的是出于自愿，有的则是纯属偶然地搬到了这里。除了都远离自己的出身地之外，他们看似没有任何共同之处。尽管如此，在最黑暗的时刻,他们给彼此的生活带来了深刻的影响。如果你不喜欢科长的《天注定》，你也不会喜欢这部荷兰的申奥片。Paradise Suite这个词是指宾馆房间里的性交易受害者被逼着满足客户的需求。这是吉雅那条线的故事，也是这部电影最重要的一条故事线。也喻指这些移民眼里的“欧洲梦”，只是套房里的事情，并不像名字听上去这么美好。"},{"id":590304,"p":"/rxw6h4XzldYwhizlM1qN98SEquF.jpg","b":"/3qd0bM8DQ7Rj32944EXnhbKROoP.jpg","t":"又见六月","r":6.5,"y":2021,"rd":"2021-05-06","hs":0.479,"d":0.472,"mt":"movie","o":"一个女人经历了医学奇迹，之后她只有几天的时间让疏远的孩子们团聚在一起，挽救家族的壁纸生意，重燃旧情。"},{"id":570358,"p":"/sLG8sjMqhcuXLyry0vB4cBGeCG2.jpg","b":"/q3Y8IeiIOuIi4FsZuzmPDB2MKYd.jpg","t":"Exil","r":5.87,"y":2020,"rd":"2020-08-20","hs":0.443,"d":0.472,"mt":"movie","o":""},{"id":855485,"p":"/e5FtkxJad6gKErNhYZJwHL8SO9w.jpg","b":"/w66CTEcXBNgtLS6j8S2YWr1PXch.jpg","t":"Jungle Cry","r":8.3,"y":2022,"rd":"2022-05-20","hs":0.526,"d":0.472,"mt":"movie","o":""},{"id":77283,"p":"/afW2tM8Gw7BTfIIfj4AcXydNhu6.jpg","b":"/idlu9jCRsKeUbYFPHIyd5L7R9OQ.jpg","t":"Lawless Heart","r":5.094,"y":2002,"rd":"2002-06-28","hs":0.234,"d":0.472,"mt":"movie","o":""},{"id":5473,"p":"/stSHfy0JaA6FGslxgv5KcWdPqyR.jpg","b":"/1VKzDyry0hxHAmpFSiTCSi3a5vS.jpg","t":"De Dominee","r":6.1,"y":2004,"rd":"2004-09-02","hs":0.244,"d":0.472,"mt":"movie","o":""},{"id":459719,"p":"/yrKsUfMS7kK2CukFJ8ZqFfClRYS.jpg","b":"/uoKL5rkyAsZncL7IvqTlkymNuKV.jpg","t":"തൊണ്ടിമുതലും ദൃക്സാക്ഷിയും","r":7.1,"y":2017,"rd":"2017-06-30","hs":0.372,"d":0.472,"mt":"movie","o":""},{"id":38866,"p":"/1zGJU0LGCUCJDpD3NIesesOTnus.jpg","b":"/cygblFiMmXMeVRVcTQEiRIBa0T9.jpg","t":"Between Strangers","r":5.938,"y":2002,"rd":"2002-08-30","hs":0.234,"d":0.472,"mt":"movie","o":""},{"id":38294,"p":"/4fOyUtW8cosQZy4JnfzNyIlkR8I.jpg","b":"/npuiLeBAjMF1PpJhLpwWqpt0I8M.jpg","t":"年少轻狂","r":6.613,"y":2000,"rd":"2000-11-03","hs":0.226,"d":0.471,"mt":"movie","o":""},{"id":46773,"p":"/4PAD20elLEHQJjl9PuRnnHLh8OQ.jpg","b":"/6CiQYtwq2YBYnyPj2khGVYOTW7Q.jpg","t":"花样少年","r":7.2,"y":2005,"rd":"2005-07-13","hs":0.25,"d":0.471,"mt":"movie","o":"生长在菲律宾贫民窟的Maxi（Nathan Lopez饰），今年12岁，外形却已十分女性化。他的父亲及两个哥哥从事黑市的手机贩卖生意，而母亲早逝的他，就负责家中所有「女人要做的工作」。平常的Maxi，也会与他的「姐妹」们一起玩耍，扮演选美比赛，或观赏电影DVD。\r 有一天，Maxi竟遇到了他心目中的白马王子──新上任的警官Victor（J R Valentine饰），在Maxi被两个流氓欺负时「拯救」了他，而Maxi也因此喜欢上了英俊威猛的Victor。\r 不幸的是，Maxi的亲人与Victor却处在黑白两道，Maxi爱慕警官的行为，为他的家人带来了额外的麻烦……"},{"id":57521,"p":"/duidHecJLf8CbdTTMc5oHaN9u14.jpg","b":"/ywScdkxr19Gggsr3u9o0Ped0srS.jpg","t":"黑色面包","r":6.722,"y":2010,"rd":"2010-10-10","hs":0.284,"d":0.471,"mt":"movie","o":"影片背景设置在西班牙内战刚刚结束的艰难时期，在加泰罗尼亚的乡间，有一名叫做安德鲁的男孩，在森林中发现了一对父子的尸体。当当局把罪名加到他父亲头上时，安德鲁决定独自行动，找到杀害那对父子的真正凶手。在这过程中，安德鲁看清了大人们用谎言构筑的世界，为了活下去，他必须学会背叛，发掘出自己内心深处的恶魔。"},{"id":221801,"p":"/1OeU7vYojFopPUvh9wjNgUx1uhG.jpg","b":"/myYMBzPXgeZ3zPnYtyUB1dYvxgU.jpg","t":"赤裸而来","r":5.8,"y":2013,"rd":"2013-09-13","hs":0.311,"d":0.471,"mt":"movie","o":"　　在接到一通意外的电话后，姐姐劳拉（Karmine Alers 饰）和弟弟艾略特（Ryan Vigilant 饰）赶回乡间别墅，准备接病入膏肓的母亲回纽约治疗。然而他们发现别墅已然入住了一位年轻英俊的看守人泰德（Benjamin Weaver 饰）。母亲由于政坛丑闻从无限风光跌落，开始平和的面对死亡。她希望子女能追逐梦想，过自己想过的生活。然而劳拉的婚姻正面临触礁，艾略特与泰德发生不恰当的性关系，就连泰德自己也有着不能说的秘密。人与人之间可能要埋葬很多过往，才能最终真正看清对方......\r 　　一部关于爱、家庭和希望的独立电影，亲情和爱就像舒缓而绵长的纽带，将所有人联系在了一起。"},{"id":409254,"p":"/jSEQrbrHbimWiSr5NmoUtNCaIrp.jpg","b":"/7D3mPNjf8l872N1S1aWBLAp2S7Y.jpg","t":"మజ్ను","r":6.2,"y":2016,"rd":"2016-09-23","hs":0.353,"d":0.471,"mt":"movie","o":""},{"id":461515,"p":"/fuyJspYn7UpG745eMpX3S9vCncg.jpg","b":"/uUXPIJ50zETecfaJB9WLBQ2TBCO.jpg","t":"我的名字是连尼","r":5.8,"y":2017,"rd":"2017-06-09","hs":0.37,"d":0.471,"mt":"movie","o":"这部电影记叙了连尼·麦克林的一生。二十世纪七十年代，伦敦东区，连尼是一名年轻的街头斗士，他与罗伊·肖经过三场无执照拳击大赛，最终获得冠军头衔“老大”。1998年，连尼客串了电影\"两杆大烟枪\"，在票房排行榜排第一的同一天，兰尼的自传也占了榜首地位。"},{"id":302431,"p":"/fz6d1MFMn2qkkjNQUtFxq7HJsqk.jpg","b":"/1yD7scPEKxKugzgn8Ydcua2odza.jpg","t":"绘者人生","r":6.2,"y":2014,"rd":"2014-11-07","hs":0.325,"d":0.471,"mt":"movie","o":""},{"id":13430,"p":"/yA4UEPUYJwE6UdKzHqD4LiSqkny.jpg","b":"/gURfAPPoAQHSaplYV18uiPdz7Wb.jpg","t":"永远的三丁目的夕阳","r":7.568,"y":2005,"rd":"2005-11-11","hs":0.251,"d":0.471,"mt":"movie","o":"在东京下野有一间叫铃木的汽车修理店，店主叫铃木则文（堤真一 饰），他与妻子友枝（药师丸博子 饰）、儿子一平生活幸福和睦。一天，他们迎来了从乡下到大城市工作的星野六子（堀北真希 饰）到店里打工，满心以为回到大公司工作的六子来到店里之后非常失望，但她还是很虚心的留下打工。期间他则文对六子有过误会，但冰释前嫌之后4人成为了一家人。六子在圣诞节收到了铃木一家送的车票，她可以在新年期间回家，但她却哭着把票退给了铃木先生……"},{"id":337107,"p":"/a8Q1XxOdAsch0yEwuhTTasUnaqd.jpg","b":"/bBl5kEyRs4YKAIn3lFa95hyhA1e.jpg","t":"爱之谷","r":5.891,"y":2015,"rd":"2015-06-17","hs":0.334,"d":0.471,"mt":"movie","o":"杰拉德（杰拉尔·德帕迪约 Gérard Depardieu 饰）和艾利（伊莎贝尔·于佩尔 Isabelle Huppert 饰）是一对结婚多年的夫妻，两人共同养育着儿子，一家人生活在宁静和稳定之中。然而，某一日，厄运从天而降，两人的儿子在一场意外之中死去，他们唯一的精神支柱断裂了。"},{"id":185357,"p":"/izErrnZhCWHOaDUjRnpbqW4gU63.jpg","b":"/ns2741hZmzZQDHH3DeK2fNmRNdJ.jpg","t":"眼中沙","r":7.5,"y":2003,"rd":"2003-08-09","hs":0.239,"d":0.471,"mt":"movie","o":"《眼中沙》根据罗宾德拉纳特·泰戈尔的小说《碧娜蒂尼》改编。"},{"id":584249,"p":"/5TIXQBVDWH2RyjSkhFBFgZrPoxg.jpg","b":"/ntJ4LSvFbNGDK6hd9BA7ZBbv7PC.jpg","t":"仆人","r":5.6,"y":2020,"rd":"2020-11-12","hs":0.441,"d":0.471,"mt":"movie","o":"入围第70届柏林电影节奇遇单元。"}]