[{"id":240932,"p":"/lIhkV9LNwViVD2bylPTFQvDD21e.jpg","b":"/iKQm68NeKhrQMV7sbP2Ivmtm1Uk.jpg","t":"百变王牌","r":7,"y":2024,"rd":"2024-01-10","hs":5.295,"d":19.515,"mt":"tv","o":""},{"id":111803,"p":"/erPcjgEmBUJQY1uz7UOeRNzKQSu.jpg","b":"/rCTLaPwuApDx8vLGjYZ9pRl7zRB.jpg","t":"白莲花度假村","r":7.609,"y":2021,"rd":"2021-07-11","hs":5.292,"d":59.312,"mt":"tv","o":"在一周的时间里，随着每一天的过去，在一个独特的热带度假村中跟踪各种客人和员工的事迹，这些完美的旅客、酒店开朗的员工和田园诗般的地方本身都呈现出一种更黑暗的复杂性。"},{"id":202308,"p":"/lLRC3GSYiFVHsxgc9tvmR6WjcOu.jpg","b":"/wge5FrHo6GLb4RpP9Ud1VvjEQap.jpg","t":"警戒","r":7.413,"y":2023,"rd":"2023-01-08","hs":5.285,"d":31.202,"mt":"tv","o":"《警戒》是一部关于费城警察局失踪人口调查组(MPU)的剧情片。每一集都讲述了一场惊心动魄、生死攸关的寻人行动，与此同时，警察杰森·格兰特和他的前妻尼基·巴蒂斯塔也在寻找他们失散多年的儿子的真相。"},{"id":202411,"p":"/4XB5XW0WDn2PYoPpBzGfZMX7qml.jpg","b":"/t9i4Icf1LsGIgkpnokQaC4hzxLa.jpg","t":"Monarch: Legacy of Monsters","r":7.763,"y":2023,"rd":"2023-11-16","hs":5.279,"d":26.762,"mt":"tv","o":"在经历了哥斯拉对旧金山的袭击并幸存下来之后，凯特再次被一个惊人的秘密震撼。在巨大的威胁面前，她踏上环球冒险之旅，以了解关于她的家庭和神秘帝王组织的真相。"},{"id":73586,"p":"/8MndvwyeV98cd8jgcMe7BkDDAv0.jpg","b":"/hFFAYkK8XkvIlQss9GYxo8TOhFi.jpg","t":"黄石","r":8.252,"y":2018,"rd":"2018-06-20","hs":5.257,"d":100.53,"mt":"tv","o":"约翰·达顿是达顿家族的一家之长，坐拥着美国最大的牧场，与牧场毗邻的有美国首个国家公园、印第安人保留地以及土地开发商买下的地皮。在一次因牲畜误入印第安人保留地引起的争端中，不幸的意外伤亡事件发生，一场涉及多方的争端在蒙大拿州这片美丽的土地上拉开了序幕。"},{"id":220801,"p":"/4OjLf98dEePgDjNywZsxlCZO1BL.jpg","b":"/v9OgLxYCq5newNdtF8dQAFENs4l.jpg","t":"愚弄至死","r":7.2,"y":2024,"rd":"2024-01-01","hs":5.257,"d":18.66,"mt":"tv","o":"丈夫遭人殺害後，前軍人瑪雅竟在嬰兒秘密監視器上看到他的身影，這才發現一場致命陰謀正悄悄逼近，所有往事都有蹊蹺。"},{"id":71790,"p":"/9Ph9qcOQvflghvx5izLUkwDUOwV.jpg","b":"/7j4ug9B6JXVeh5HhQjjPScrdj4Z.jpg","t":"SWAT反恐特警組","r":8.067,"y":2017,"rd":"2017-11-02","hs":5.251,"d":154.6,"mt":"tv","o":"故事敘述「反恐特警組」為洛杉磯警察局中最菁英的部隊，他們的主要任務是保護城市，並專門處理一般警察難以應付的重大案件。"},{"id":157744,"p":"/vNJWr0xh7W5IDzFTnVzWhw6KoJr.jpg","b":"/vIioWssbxRtEkIzgj8r0pCWYkYM.jpg","t":"1923","r":8.21,"y":2022,"rd":"2022-12-18","hs":5.248,"d":38.036,"mt":"tv","o":"本剧讲述 Dutton 家族的另一个世代，他们经历了包括西进运动、禁酒令和大萧条在内的各种困难时期，为了克服当时的种种艰辛而奋斗的故事。"},{"id":110492,"p":"/hz6LZSqSDOia7ahTvHP310Vhiuj.jpg","b":"/pj1wFbZF3gpEg7F0EreXTvZNZTG.jpg","t":"和平使者","r":8.245,"y":2022,"rd":"2022-01-13","hs":5.246,"d":30.14,"mt":"tv","o":"和平使者被救回去之后原以为自己获得了自由，结果却被安排执行新的任务——蝴蝶计划。"},{"id":93740,"p":"/kNYbxPW4opiaPJuonbgfFKUzMOg.jpg","b":"/7NNNXo0qG2SqH4JoG7GPvJ2hzes.jpg","t":"基地","r":7.8,"y":2021,"rd":"2021-09-23","hs":5.242,"d":52.923,"mt":"tv","o":"講述在銀河帝國日漸衰落之際，一群流亡者踏上艱困的旅途，他們不僅要拯救人類，還要重建文明。"},{"id":243006,"p":"/mgn4Vxx5PHIcKUBSsSecDlahIBH.jpg","b":"/cJIW5VtjipFbvmA6moBjGCn7pz8.jpg","t":"海军罪案调查处：起源","r":7.6,"y":2024,"rd":"2024-10-14","hs":5.239,"d":18.741,"mt":"tv","o":"该剧讲述了跟随年轻的勒罗伊·杰思罗·吉布斯 （Leroy Jethro Gibbs） 在 NCIS 彭德尔顿营办公室开始他的职业生涯，成为一名新特工。"},{"id":97546,"p":"/4heF8RihtkN67AhvnT7kWfrCl7t.jpg","b":"/8rDij8tYynUfu2hMVXynAp2pSjY.jpg","t":"乜都得教練","r":8.393,"y":2020,"rd":"2020-08-14","hs":5.228,"d":56.893,"mt":"tv","o":"美式足球教練泰德拉素，受聘前往英格蘭擔任英超足球隊教練。由於毫無相關執教經驗，他未能獲得球員及當地球迷的信任，但他誓要向大家證明：我是乜都得！"},{"id":133813,"p":"/eBGkwxzoFZReuJuDkpcfQkuqsXn.jpg","b":"/8Xh6YJr2VS66EiifbtDYV3ZgoVT.jpg","t":"海上密室谋杀案","r":6.535,"y":2024,"rd":"2024-01-16","hs":5.219,"d":19.032,"mt":"tv","o":"故事以全世界前1%的富豪为背景，因为种种的阴错阳差，Imogene成为了豪华邮轮上一起密室谋杀案的头号嫌疑犯，为了证明自己的清白，她必须与侦探Rufus合作破案，但在这艘奢华的地中海邮轮上，所有娇生惯养的宾客和疲惫不堪的员工都有嫌疑。"},{"id":85552,"p":"/2fQXV9wqD63IrZlfNqMkFzx2pkT.jpg","b":"/9KnIzPCv9XpWA0MqmwiKBZvV1Sj.jpg","t":"亢奋","r":8.3,"y":2019,"rd":"2019-06-16","hs":5.214,"d":63.327,"mt":"tv","o":"在一年前有个青少年在夜总会外被谋杀，而悲剧发生一年后其他青少年同伴试图通过毒品、性爱和暴力来逃避现实，以应对无法确定的未来。"},{"id":72710,"p":"/nFTo0VJbV97aFuIoZrhfLdeCike.jpg","b":"/1gajPADcRyzmYvfAefbJwhCy4bk.jpg","t":"大陆酒店","r":7.452,"y":2023,"rd":"2023-09-22","hs":5.208,"d":27.85,"mt":"tv","o":"本剧是一部叙事连续剧，揭示了处于约翰·维克所在的世界里那家标志性刺客酒店的暴力起源。20世纪70年代的纽约，温斯顿·斯科特招募了一支团队来应对因自己哥哥袭击大陆酒店而引发的巨大阴谋。这部血腥动作剧探讨了亲情、命运与复仇间的碰撞。"},{"id":279603,"p":"/sPO6rruv6ZmSn5VXYv2M0IqKrNs.jpg","b":"/mPhSRv8Ni5Izz3B90TQZhA4Il16.jpg","t":"奇探佩辛丝","r":7.96,"y":2025,"rd":"2025-01-08","hs":5.199,"d":10.196,"mt":"tv","o":"佩辛丝·埃文斯从事文书工作，负责整理警方记录。她是一名患有自闭症的女性，对解决谜题特别感兴趣，对犯罪学有着神秘的迷恋和天赋——她独特的视角使她能够通过线索将线索串联起来，而其他人根本无法做到这一点。"},{"id":94028,"p":"/fCTLiqk9xMvxg2aoOFu959vyfi1.jpg","b":"/Av4ku3UIoWBbxNxKjXrFohMS6xi.jpg","t":"雷普利","r":8,"y":2024,"rd":"2024-04-04","hs":5.177,"d":16.69,"mt":"tv","o":"一個騙徒在義大利接到特殊工作，一腳踏進了財富和特權的世界。但想要保住這夢寐以求的生活，他必須羅織層層謊言。"},{"id":75219,"p":"/v84k5An0TPKhiH7oXTboE9UOBXa.jpg","b":"/nU5nByGzsPTXm2w4WdMFtE6YU14.jpg","t":"火速救援最前線","r":8.217,"y":2018,"rd":"2018-01-03","hs":5.171,"d":95.259,"mt":"tv","o":"故事聚焦於用自己的生命來拯救他人的第一線人員：警察、輔助醫護人員、消防員以及接線員的生活與職涯。取材自急救人員真實的高壓工作經驗，他們經常深入刺激、緊張、不可預測又膽顫心驚的險境。劇情將描繪這些拯救弱勢人們的第一線人員，如何在工作之餘，解決自己的人生難題，並從中取得平衡。"},{"id":197125,"p":"/vl0HKRKxOzfQVQAAt4HgvDfVyVX.jpg","b":"/pIGLdSGbdBAKu5diYFkU5nLpXkI.jpg","t":"Constellation","r":7.107,"y":2024,"rd":"2024-02-21","hs":5.159,"d":17.801,"mt":"tv","o":"国际太空站发生致命意外，一名单独奋战的宇航员凭借英勇的表现成功返回地球，却发现自己生活中的关键记忆，包括她年幼的女儿，都发生了变化。"},{"id":132750,"p":"/tJX18h8pYsVW9GpTeMfjbI2aIj4.jpg","b":"/rtujL4mutqlzk7ELbkyJhLfUbEX.jpg","t":"死亡男孩偵探社","r":7.8,"y":2024,"rd":"2024-04-25","hs":5.156,"d":16.9,"mt":"tv","o":"兩個少年鬼和一個會通靈的少女合作，為靈界客戶破解大大小小的謎團，豈料半路殺出法力高強的女巫來攪局。"},{"id":232342,"p":"/xXpPzeaVgjB4wnOlaQAg70U9aWY.jpg","b":"/pp4jnkOneeb4FFcni9VUCyo18sZ.jpg","t":"毒鎮","r":6.9,"y":2025,"rd":"2025-02-27","hs":5.154,"d":10.048,"mt":"tv","o":"科比鎮的幾十位母親都生出帶有殘疾的寶寶，她們團結起來挺身抗爭，要始作俑者負起責任。"},{"id":213338,"p":"/wXX2V4L8ZXZY50BDYf6Cq393yPB.jpg","b":"/iAnNhCoBKUXWoTxgmGYrv2Qc8Dm.jpg","t":"上流戀愛家","r":7.558,"y":2023,"rd":"2023-11-08","hs":5.148,"d":28.237,"mt":"tv","o":"一群愛玩的美國女孩在1870年代嚴肅死板的倫敦驚艷登場，引發起英美文化衝突。她們被派來覓得丈夫和社會地位，但她們心裏渴望的遠不止如此。"},{"id":203744,"p":"/eEHHRRK0gXyMxlJH3SJRqsBnFYX.jpg","b":"/ipNCnwKaRqyddXRukTslsl3hiop.jpg","t":"洛城奇探","r":7.222,"y":2024,"rd":"2024-04-04","hs":5.147,"d":17.574,"mt":"tv","o":"一位神秘私家偵探調查荷里活製作人心愛孫女失蹤一案，同時也要面對自己的心魔。"},{"id":121658,"p":"/1Ublm6D8zmqMroqrXkn3Fgd353q.jpg","b":"/8JtKCIBzf3AYbsxBFSL74NoGH2u.jpg","t":"聯邦調查局FBI：國際探員","r":7.7,"y":2021,"rd":"2021-09-21","hs":5.145,"d":58.862,"mt":"tv","o":"《聯邦調查局FBI：國際探員》為《聯邦調查局FBI》（FBI）第二部衍生劇，以 FBI 國際部門的菁英探員作為主角，描述他們在世界各地執行保護當地美國人的任務。"},{"id":131835,"p":"/eBHzItKQNfPdt2GL4LcHJy8P1sH.jpg","b":"/8pWGfg6siFjgWJahhkrzGDz1UDs.jpg","t":"鸚鵡螺號","r":6.913,"y":2024,"rd":"2024-10-25","hs":5.131,"d":17.707,"mt":"tv","o":"是一部由詹姆斯·多默創作的英美十集冒險電視劇。它改編自儒勒·凡爾納 1870 年的小說《海底兩萬裡》，講述尼莫船長的起源故事：一位被剝奪了與生俱來的權利和家庭的印度王子，一名東印度商業公司的囚犯，以及一個決心向奪走他一切的勢力復仇的人。"},{"id":116135,"p":"/ar1bzYhFc3U2quUFX2GCchp9F2g.jpg","b":"/k47JEUTQsSMN532HRg6RCzZKBdB.jpg","t":"维京传奇：英灵神殿","r":7.705,"y":2022,"rd":"2022-02-25","hs":5.122,"d":36.094,"mt":"tv","o":"在这部《维京传奇》的续集中，新一代的传奇英雄们在一百年后崛起，书写自己的命运，创造不朽的历史。"},{"id":129398,"p":"/ebWAAQTUUQlvdIB5bhMNrxjdeCX.jpg","b":"/yBYkOSSNwd5Vrh0rF18RlJbyooF.jpg","t":"同情者","r":7,"y":2024,"rd":"2024-04-14","hs":5.121,"d":17.564,"mt":"tv","o":"改编自阮清越的普利策获奖同名小说，是一部间谍惊悚兼跨文化讽刺类型的剧集。讲述了一名法越混血的越共间谍在越战最后几天里的斗争，以及他作为难民在洛杉矶的新生活，在那里他了解到自己的间谍生涯并没有结束。"},{"id":58841,"p":"/xItCI9QZ1RmnL0zy2mTT03eHJpW.jpg","b":"/cFZYtCx54BmFXe4wExts2tPnPHh.jpg","t":"芝加哥警署","r":8.414,"y":2014,"rd":"2014-01-08","hs":5.115,"d":209.779,"mt":"tv","o":"芝加哥警署的第21辖区有两组完全不同的警察。其中一组是穿制服的警察，负责在街道上巡逻，直接打击和处理街头犯罪行为。另一组被称作情报组，负责打击危害这座城市的主要毒瘤——黑帮犯罪、毒品走私、高级别谋杀案，诸如此类。负责领导情报组的的是Hank Voight警官（Jason Beghe）。他是一个不怕破坏规矩的人——只要能维护正义，哪怕和法律对着干他也在所不惜。他为人强悍，要求严格，只有那些能上得刀山下得火海的人才能在他的手下当差。就拿Antonio Dawson侦探（Jon Seda）来说——尽管他与上司有过一段复杂的历史，但他对于指挥这样一个团队充满雄心。即便那意味着他每天都要和Voight闹矛盾，也阻止不了他要留下来的决心。那些街头巡警每天都在盯着情报组看，他们梦想得到升职并加入这个精英团队。而对于已经身在其中的人来说，这份工作每天都意味着挑战，他们必须为这座城市保驾护航并承担巨大的责任。有些时候责任会变成压力，而压力会带来心理和情感上的创伤——走出第21辖区的办公室，走入这些侦探的个人生活，你就会明白这句话的含义。"},{"id":212246,"p":"/8PW2duuf99QcWfhr8RH2VgJ0uHO.jpg","b":"/5y4cSOkBHoacJbymwldlDQtdN1W.jpg","t":"內景唐人街","r":7.3,"y":2024,"rd":"2024-11-19","hs":5.114,"d":17.396,"mt":"tv","o":"《內景唐人街》講述威利斯吳的故事。他長期在警匪劇中跑龍套，但他胸懷大志。在此過程中，他發現自己生活在一個光怪陸離的世界中，他揭開了其中的各種秘密以及家族隱秘的歷史。"},{"id":247784,"p":"/uGKTDr8ruc4IHGsEZ8wSQZpy2eN.jpg","b":"/52RLQclQ6XHiu6QiSKAwb58TmCs.jpg","t":"心跳一線間","r":7.794,"y":2025,"rd":"2025-04-03","hs":5.073,"d":9.489,"mt":"tv","o":"在這間邁阿密醫院裡，一群急診住院醫師必須應付緊急醫療狀況與私人恩怨，同時院內還出現了一樁引發分歧的指控。"}]