[{"id":101881,"p":"/cmVS5lcu9I1a2qMaA0TR38kSnJs.jpg","b":"/81w1zfORrbUqqtm7vGos67EvBxu.jpg","t":"主席","r":7.2,"y":2020,"rd":"2020-06-05","hs":2.846,"d":10.692,"mt":"tv","o":"　　卡拉·苏扎(《逍遥法外》)将主演亚马逊新剧《主席》(El Presidente)，聚焦国际足联FIFA的丑闻，共8集。帕布罗·拉雷恩(《追捕聂鲁达》《第一夫人》)的制片公司Fabula制作，阿尔曼多·博(《鸟人》《美错》)执导。基于2015年国际足联丑闻，从一个三流智利足球俱乐部主席Jadue的角度来探讨这一事件：他在臭名昭著的前国际足联第一副主席、阿根廷足协主席胡利奥·格隆多纳的手下，从一个默默无闻的人成为一起1.5亿美元贿赂阴谋的关键人物。"},{"id":72296,"p":"/qGXd58PIikQdX5vDXecAMgns6w6.jpg","b":"/7GH07BPyejfwVj64lwHjQOUaWtZ.jpg","t":"第一次的辣妹","r":8.383,"y":2017,"rd":"2017-07-12","hs":2.846,"d":15.749,"mt":"anime","o":"　　如果与守备坚固的辣妹交往的话！？全是初体验的“辣妹×非现充少年”交往的辣妹恋爱喜剧！\n\n　　新学期——那是新的邂逅的季节。在放眼望去尽是情侣的教室里，羽柴纯一苦恼着。“为啥我还是DT童贞啊！？”为了DT毕业这一夙愿，最快的捷径是向辣妹下跪拜托，从朋友那里听闻此事的纯一，向同班的辣妹·八女由佳奈下跪并告白！！结果由佳奈的回复竟然是OK！？纯一的命运究竟将如何？？"},{"id":212921,"p":"/bf60KTbhfAKkZASoLDLHVAZfJ3v.jpg","b":"/jAp4HEecU2GCUkeDplt5OpWw8dM.jpg","t":"我讨厌圣诞节","r":6.5,"y":2022,"rd":"2022-12-07","hs":2.846,"d":7.185,"mt":"tv","o":"一名单身护士骗家人说自己有男朋友，于是拼命想在圣诞节前找一个，然而圣诞节就在24天后。"},{"id":2777,"p":"/mA2apmkA0GZiPxBWDNjhVZb8SOE.jpg","b":"/fVO7r9tAnauny8DAqbetlQ1tVtu.jpg","t":"肥猫大战三小强","r":7.4,"y":1999,"rd":"1999-09-06","hs":2.845,"d":131.838,"mt":"anime","o":"一隻叫 Oggy的貓，藍色皮膚紅鼻子，面臨著一群惱人的小強（蟑螂）的騷擾。"},{"id":29422,"p":"/2SShbsKfkBWWecKEN0fgiYtz7IZ.jpg","b":"/cGRvrH5HAm9wKXy99MHBP9EMc46.jpg","t":"第三者","r":6.4,"y":2020,"rd":"2020-06-12","hs":2.845,"d":10.948,"mt":"tv","o":""},{"id":202432,"p":"/wxR3Yskt1Lc2lXRmxMK8YrzmbKs.jpg","b":"/pE4oNDTiqgoamQlH7ymJiQd2svE.jpg","t":"关于爱我所知道的一切","r":5.727,"y":2022,"rd":"2022-06-07","hs":2.845,"d":7.145,"mt":"tv","o":"　　本剧改编自Dolly Alderton的同名畅销回忆录，聚焦两个童年密友，Maggie (Emma Appleton饰)和Birdy (Bel Powley饰)。故事以2012年伦敦的合租房为背景，混合对21世纪初郊区青春期的回忆，毫不掩饰地深入探讨了糟糕的约会、心痛和羞辱。"},{"id":42509,"p":"/6iysgZr6Upm5RlAlVFo5f4D9euu.jpg","b":"/gDvxT2z6TNxervG97WfpePRZ3aR.jpg","t":"命运石之门","r":8.4,"y":2011,"rd":"2011-04-06","hs":2.845,"d":30.572,"mt":"anime","o":"本作主人公冈部伦太郎（宫野真守 配音）是个患有严重中二病的大学生，自称为“凤凰院凶真”的他和伙伴们组成了“未来发明研究所”，在位于秋叶原的一个简陋实验室内进行各种古怪发明和调查。2010 年 7 月 28 日这天，冈部和青梅竹马真由理（花泽香菜 配音）一同去了科学讲义会场，在那里，他们遇见了天才少女牧濑红莉栖（今井麻美 配音）。让人意想不到的事情发生了，冈部在会馆楼道内听到一声惨叫，他闻声而至，发现了倒在血泊中的牧濑。冈部用手机短信将这件事告诉好友桥田至，这个举动，让世界都颠覆了。实验室里那个所谓的“未来道具”，竟然真的可以左右世界的进程，冈部自此成了孤独的观测者。这一切都是命运石之门的选择。"},{"id":70748,"p":"/spWAmOI88ymmYzwWTUepfKxtNl3.jpg","b":"/3Z2iKz1qcylKzhoQum8aN52MtIL.jpg","t":"奖金家族","r":6.6,"y":2017,"rd":"2017-01-30","hs":2.843,"d":18.35,"mt":"tv","o":"丽莎（Vera Vitali）和帕特里克（Erik Johansson）是一对30多岁的夫妇，他们分别居住在斯德哥尔摩，最近与前妻离婚；两人都有10岁的儿子，丽莎（Lisa）有一个十几岁的女儿。Patrik的前妻Katja（Petra Mede）是建筑师，Lisa的前夫Martin（Fredrik Hallgren）在一家床铺零售商工作。该系列讲述了新夫妇与前妻之间动荡的关系，以及三个孩子对新家庭状况的调整，以及帕特里克如何处理安静勤奋的儿子威廉（Jacob Lundquist）与丽莎麻烦，冒险的对比。儿子埃迪（Frank Dorsin"},{"id":114439,"p":"/9e2zBDDJNzwKymAWDuLhgViPc06.jpg","b":"/3RC0M5ynmtrGRJBkQcYi0kjxD64.jpg","t":"Let's Make a Deal","r":4.9,"y":2009,"rd":"2009-10-05","hs":2.842,"d":52.746,"mt":"tv","o":""},{"id":211,"p":"/zmvRaCRcmi6lsriYxZmAR6uWHPS.jpg","b":"/lW3RCsfXXVGIBXyupMGT7dAYcze.jpg","t":"橄榄球之恋","r":7.718,"y":2006,"rd":"2006-10-01","hs":2.84,"d":70.42,"mt":"tv","o":"《橄榄球之恋》（The Game）是由玛拉·阿基尔原创，凯尔塞·格拉玛担任制片的美国喜剧剧情电视剧。该剧首映于2006年10月1日，是CW电视台在黄金时段首播的唯一一部新喜剧连续剧。作为该电视网播出的第一年，该剧同《Runaway》是仅有的两部非继承于其前身WB电视台和联合派拉蒙电视网（UPN）的电视剧。该剧是UPN/CW长寿喜剧《女友们》的衍生剧。"},{"id":124073,"p":"/dnz8XLoesHeQtgeKf4Aftcoqgf6.jpg","b":"/gtIJjX1q22bE0Gjht5hJVzc23Lx.jpg","t":"尸咬","r":6.82,"y":2021,"rd":"2021-05-21","hs":2.84,"d":8.879,"mt":"tv","o":"剧中讲述全球深陷新冠疫情之中，一种虚构的新冠病毒变异毒株，似乎会令感染者成为丧尸。"},{"id":101214,"p":"/8KrhN7Mx6uoxFnRAaZrzYRO5TVB.jpg","b":"/bJbh9BT53az3uWortxzfvVcigJG.jpg","t":"Some Good News","r":6.2,"y":2020,"rd":"2020-03-29","hs":2.84,"d":10.895,"mt":"tv","o":""},{"id":96718,"p":"/k2T6PmKcTIZRvNAP5LV81MekoPf.jpg","b":"/i5T7MjQHADTKMeYlQce70JI5d9l.jpg","t":"世代","r":7.173,"y":2021,"rd":"2021-03-11","hs":2.838,"d":8.796,"mt":"tv","o":"　　genera+ion是一群高中生的研究对象，他们对现代性行为（装置和所有）的探索，在他们保守的社区里，测试了他们对生活、爱和家庭本质的根深蒂固的信念。"},{"id":73549,"p":"/yRVaHKUbUF7e97po0fulgG4yM3h.jpg","b":"/4PehC4usZ8PoChlUP3Y5TI4KaQF.jpg","t":"金牌小特工","r":6.6,"y":2014,"rd":"2014-11-26","hs":2.837,"d":28.123,"mt":"tv","o":""},{"id":53606,"p":"/wvtW9YoMkovpMqyZCWUbQC6FJlg.jpg","b":"/jHaZMdEQVZUKsfE3yCZ1atSXEWw.jpg","t":"爱·恋","r":7.164,"y":2016,"rd":"2016-02-19","hs":2.836,"d":20.765,"mt":"tv","o":"这部由贾德·阿帕托等人打造的喜剧风格大胆。个性叛逆的米琪遇上了温和敦厚的格斯，他们虽然性情迥异，却一同经历了现代爱情世界里的种种欣喜和苦楚。"},{"id":84282,"p":"/12kJ01sCBVcR1Z4AgOa5Q2Beq44.jpg","b":"/wrWC1FIwC7h3kMxP7RzbQPivlXw.jpg","t":"四个婚礼和一个葬礼","r":7,"y":2019,"rd":"2019-07-31","hs":2.836,"d":13.009,"mt":"tv","o":"Hulu限定剧《四个婚礼和一个葬礼 Four Weddings and a Funeral》根据同名英国电影改编，由Mindy Kaling负责执笔，与Matt Warburton同当制片。类似电影版，《四个婚礼和一个葬礼》讲述四位在伦敦重聚的美国朋友Maya（Nathalie Emmanuel饰演，代替Jessica Williams）﹑Craig（Brandon Mychal Smith饰演）﹑Ainsley（Rebecca Rittenhouse饰）及Duffy（John Reynolds饰），他们的生活将因为一记震撼弹而受到影响，然后交织成四个婚礼和一个葬礼。\n\n　　《四个婚礼和一个葬礼》电影版演员Andie MacDowell饰演Ainsley的母亲﹑其他包括演员Nikesh Patel﹑Zoe Boyle﹑Jennie Jacques﹑Harish Patel及Guz Khan。"},{"id":42410,"p":"/uhF64KTlRDu7pelWdXNvunrGUrr.jpg","b":"/kH9iK6krt0VBwAv5xbsYyhn8AW5.jpg","t":"无头骑士异闻录","r":7.7,"y":2010,"rd":"2010-01-08","hs":2.835,"d":43.256,"mt":"anime","o":"东京，池袋。\n\n向往都市生活的少年龙之峰帝人接受从小一起玩到大的好友纪田正臣邀约离开家乡来到东京进入池袋来良学园上学。\n\n而在池袋有几个绝对不能招惹的人物，尤其是被誉为“最强”的平和岛静雄和经营情报屋的折原临也这两个人。另外，池袋有一个正体不明的暴力组织，名叫“Dollars”。\n\n然而，就在上京的第一天，因为对池袋复杂的关系而感到不安的帝人就亲眼目睹了骑着黑色摩托在街头穿行的都市传说“无头骑士”——塞尔提·史特路尔森。\n\n于是，随着池袋接连发生了砍人魔事件，平和岛静雄、折原临也、Dollars、无头骑士、砍人魔、黄巾贼等陆续浮出水面，围绕着“谁是池袋最强”的话题，池袋正面临着崩坏中，一连串不正常但爽直的故事开始了。"},{"id":127651,"p":"/zR6A3jFMjakrQZPmWNvMCelcWYr.jpg","b":"/9BVg5pCrIM7tPk8DF8MoTz05W1s.jpg","t":"来魔女食堂吧","r":7.5,"y":2021,"rd":"2021-07-16","hs":2.835,"d":8.78,"mt":"tv","o":"该剧改编自第3届教保文库故事公募大赏作具商熙作者的长篇小说，讲述了出售能够实现人们愿望的食物的魔女食堂和即使出卖灵魂也要过像魔法一般的生活的客人们的奇幻故事。"},{"id":1110390,"p":"/vwsBpnwmMO0xtIgxvCrViJgZhVj.jpg","b":"/grsqPFaIOnOERVrDykdcvzjOq4t.jpg","t":"言者无心","r":5.7,"y":2024,"rd":"2024-02-09","hs":2.835,"d":4.081,"mt":"movie","o":""},{"id":158948,"p":"/wUaA9jPyUfK0WIfu1n94KMdnGgt.jpg","b":"/obOvmqEgZY1JUV4MAeACzAqSBG2.jpg","t":"Doppelhaushälfte","r":7.421,"y":2022,"rd":"2022-03-15","hs":2.834,"d":7.033,"mt":"tv","o":""},{"id":73933,"p":"/10J9hDKtmASo9YFPUeOWYRO3ffW.jpg","b":"/cKYQKh39NHV10rhbiYRWjaY1zqp.jpg","t":"我们的故事","r":7.8,"y":2017,"rd":"2017-09-14","hs":2.833,"d":17.948,"mt":"tv","o":""},{"id":4586,"p":"/gwtzCwU2wdLLf8oejQu2TINiWfQ.jpg","b":"/8U2ndZrneigI2zkvGuTJtt1ZsxK.jpg","t":"吉尔莫女孩","r":7.9,"y":2000,"rd":"2000-10-05","hs":2.831,"d":93.694,"mt":"tv","o":"　罗蕾莱（劳伦·格拉汉姆 Lauren Graham 饰）未婚先孕，年仅十六岁便生下了女儿洛瑞（阿丽克西斯·布莱德尔 Alexis Bledel 饰），为此，她不惜与母亲艾米丽（Kelly Bishop 饰）和父亲理查德（爱德华·赫曼 Edward Herrmann 饰）决裂，离开了富有的家庭，靠着自己的倔强和努力独自抚养女儿。\n\n　　时间流逝如同白驹过隙，如今，洛瑞已然成为了亭亭玉立的漂亮姑娘，罗蕾莱亦步入中年，幸运的是，独特的成长环境和极小的年龄差距反而让洛瑞和母亲之间宛如朋友，相处起来轻松又自然，同时，品学兼优的洛瑞拥有着考入哈佛大学新闻系的远大理想。亲情，友情，爱情，成长，在每一个人的生命里都留下了无法磨灭的印记。"},{"id":153950,"p":"/iKotSJFbBHHRe7V804MhJLZMKv9.jpg","b":"/wGbEvyX8hVljZW3Q19GfInyJe7b.jpg","t":"ये काली काली आंखें","r":6.519,"y":2022,"rd":"2022-01-14","hs":2.83,"d":7.051,"mt":"tv","o":"一个男子被一名有权势的政客女儿猛烈追求，后者不惜一切想得到他。他于是铤而走险，试图让自己的生活重回正轨。"},{"id":42004,"p":"/z9F78WN0li22U5G2unZ7eJ2jmIK.jpg","b":"/8o2QX6LkieNEDhaSc0ZEiGQqC25.jpg","t":"Comic Book Men","r":6.828,"y":2012,"rd":"2012-02-12","hs":2.829,"d":35.987,"mt":"tv","o":""},{"id":70813,"p":"/tYu7ymq9k8jn86Xw1ZxEuky8oXS.jpg","b":"/zTzFYUZBchlCeamtCEf0b1zWRE2.jpg","t":"三流之路","r":8,"y":2017,"rd":"2017-05-22","hs":2.828,"d":17.18,"mt":"tv","o":"不知何时开始，我们都成为了“只是那样”的大人。崔爱拉（金智媛饰）梦想成为新闻主播，却屡屡落榜，迫于现实只能在百货公司服务台工作。与爱拉青梅竹马的高东万（朴叙俊饰），虽然有着成为格斗选手的梦想，现实中却只是一名平凡的约聘员工。没钱没背景、如配角般走在三流之路上的他们，携手战胜挫折与束缚，踏上人生的康庄大道。"},{"id":30977,"p":"/7FiiNjhJr1NgCjQArQupVEP6i4s.jpg","b":"/cGgqLzBGUY0dxsE5i3W7SXBGRbe.jpg","t":"某科学的超电磁炮","r":7.3,"y":2009,"rd":"2009-10-02","hs":2.826,"d":49.983,"mt":"anime","o":"故事发生在面积占据东京都西部的三分之一，居住着 230 万名人口，其中八成人口是学生的巨大都市“学园都市”。学园都市和外部隔离，研究最尖端科技。所有学生都接受超能力开发，并大都借由药物、催眠术与通电刺激等方式取得超能力。有各种类型不同能力，以范围和威力分为无能力者（Level 0）、低能力者（Level 1）、异能力者（Level 2）、强能力者（Level 3）、大能力者（Level 4）和超能力者（Level 5）。主角御坂美琴是学园都市中仅七位超能力者（Level 5）的其中一人，排行第三。她是拥有操纵电击能力的“电击使”，因其特有的绝招（将硬币以 3 倍音速的初速发射）“超电磁炮”而得名。"},{"id":66330,"p":"/w8wO5EKdd5wNHPkOYXNpAnaqP5k.jpg","b":"/iOyiuJhKlKY4tVT8EfJ1GwnM2By.jpg","t":"W-两个世界","r":8.46,"y":2016,"rd":"2016-07-20","hs":2.824,"d":15.739,"mt":"tv","o":"身为菜鸟医生的吴妍珠（韩孝周饰）是热门漫画《W》主人公姜哲（李钟硕饰）的粉丝，然而漫画连载还剩最后一回，她的父亲、《W》的作者吴成务（金义城饰）却忽然失踪。吴妍珠在寻找父亲的过程中，意外通过父亲作画的数位板，来到了漫画《W》的世界，遇到了奄奄一息的姜哲，而此时吴成务在现实世界中也现身了。一边是吴成务在构思框架、意图迅速杀死姜哲；一边则是吴妍珠想尽办法拯救姜哲、摸索回到现实世界的方法。"},{"id":1049082,"p":"/rbjTGOKWcL6xjhTMGhRN1YNejE5.jpg","b":"/8MCBwKgWYaFjedlDHzKTPzl3HTy.jpg","t":"Jumbo","r":6.7,"y":2025,"rd":"2025-03-31","hs":2.824,"d":2.723,"mt":"anime","o":""},{"id":86632,"p":"/233gBQteUssc1GXrHfMwgFUXMWO.jpg","b":"/6lkZYlgKF77OOcsoLP6Rdj4Lwy9.jpg","t":"公关","r":7,"y":2019,"rd":"2019-02-21","hs":2.823,"d":12.843,"mt":"tv","o":"　　《公关》设定在竞争激烈的名人公关世界里，美国危机公关策略师罗宾居住在伦敦，是这一行业的专家，她的工作节奏很快，为行为不端的知名人士提供咨询，但一涉及到自身生活，罗宾就会成为一个自我破坏者。"},{"id":150540,"p":"/gN3qUaxucFWNTBDsaxkyCQSbox2.jpg","b":"/j29ekbcLpBvxnGk6LjdTc2EI5SA.jpg","t":"头脑特工队","r":7.911,"y":2015,"rd":"2015-06-17","hs":2.821,"d":16.469,"mt":"anime","o":"每个人的成长都绝非一帆风顺，莱莉也是这样。父亲因为工作原因举家搬迁到旧金山，莱莉也只得和曾经熟悉的生活说再见。和所有人一致，莱莉也是被她大脑里的五种情绪小人共同支配——乐乐、怕怕、怒怒、厌厌和忧忧。这五位情绪居住在莱莉脑海里的控制中心，在那里他们可以通过适当调配来指导莱莉的日常生活。然而搬来旧金山，全新的环境与生活都需要莱莉适应，混乱渐渐在控制中心里滋生。莱莉来到新学校的第一天，五位情绪就因为失控令莱莉在新同学面前出丑，混乱中乐乐和忧忧更被抛出控制中心，流落在莱莉的茫茫脑海。只留下怕怕、怒怒和厌厌的控制中心更加混乱，莱莉甚至无法与人进行正常沟通。乐乐和忧忧则要想尽办法要回到控制中心，力求在莱莉完全崩溃之前挽救她的生活以及家庭。"}]