[{"id":238091,"p":"/yVSBBA82TMakoLhGfL7MbSWXf8p.jpg","b":"/qqKhe0QFEDjG9COTyRbME9gkr8N.jpg","t":"富婆、管家与男友：美妆帝国继承人丑闻","r":6.8,"y":2023,"rd":"2023-11-08","hs":1.713,"d":2.091,"mt":"tv","o":"世上最富有的女人与她女儿之间的矛盾是如何演变为全国性丑闻的？这部引人入胜的系列纪录片将讲述整个故事的来龙去脉。"},{"id":146086,"p":"/8XwRryZdpr1N8fpa76kSoWSiAps.jpg","b":"/7zgHzqubU899mvbPX9r9Bbh29xB.jpg","t":"বলি","r":5.3,"y":2021,"rd":"2021-12-03","hs":1.377,"d":2.037,"mt":"tv","o":""},{"id":262154,"p":"/mlE61XHa1LlVTOdXn1hZvtlLoa7.jpg","b":"/sWtllcfhlBsmKMgaVXgwcH5v0wC.jpg","t":"Murshid","r":6.3,"y":2024,"rd":"2024-08-30","hs":1.925,"d":1.998,"mt":"tv","o":""},{"id":96676,"p":"/zCq56uFGe16RrrEl9D9lKjzdAnE.jpg","b":"/xu8eKYv1PaaiPjYIux9rL8pF64z.jpg","t":"特工女王","r":6.6,"y":2020,"rd":"2020-02-28","hs":1.257,"d":1.991,"mt":"tv","o":"　　在母亲被暗杀后，奎恩·索诺成长为一名出色而与众不同的间谍，尽心尽力保护非洲人民。在一次危险的实地任务中，奎恩无意中发现了母亲死亡的惊人细节，于是开始了自己的真相寻找之路。"},{"id":153425,"p":"/wHGYdkcV8gLBi1TLVylyR4VUho.jpg","b":"/9KLBdEE0XGybFFW49rxVG0YnlxM.jpg","t":"狱警生活","r":6.5,"y":2022,"rd":"2022-01-06","hs":1.482,"d":1.979,"mt":"tv","o":"　　本剧将呈现21世纪的英国男子监狱中，狱警们真实可怕又充满黑色幽默的生活。故事中心是处境艰难的狱警们的领头Leigh，一位女性，她把成年后的人生贡献给了这座监狱和其中麻烦缠身 的犯人。尽管自己负责的区域人满为患，处于破败的官僚主义和目光短浅造成的灾难之中，Leigh为这些囚犯做的事远在职责之外。但Leigh也有自己的秘密和一段过去，一旦被发现，要付出的代价可能远不止丢掉工作那么简单。新来的年轻狱警Rose有着自己的目的，多嘴的她是否会让Leigh完蛋，亦或是意料之外的救星？"},{"id":259739,"p":"/YFzYgd1i13RdPVH1TDsDPgy5jC.jpg","b":"/mUEZVH7sKLpHZn4O4vn1CdWhhUM.jpg","t":"埃文斯代尔女童失踪事件","r":6.8,"y":2024,"rd":"2024-08-08","hs":1.913,"d":1.976,"mt":"tv","o":"2012年在爱荷华州的埃文斯代尔，两名女童黎瑞可和伊丽莎白遭到绑架。埃文斯代尔是个质朴安静的小镇，因此这起案件震撼了整个小区。"},{"id":212294,"p":"/171wHZ0AR2rD4MqTS2QPOOM4nD0.jpg","b":"/2D61udFtYjzgzIggJHVHmgaahYi.jpg","t":"生死抉择","r":5.2,"y":2022,"rd":"2022-11-16","hs":1.461,"d":1.936,"mt":"tv","o":"福阿特·阿肯哲是一位功成名就并且备受尊崇的律师，当他的女儿遭遇不幸后，他的生活彻底发生了改变。为了复仇，福阿特按发送到他手机上的神秘信息行事，这些信息最终将颠覆他的生活，逼他在黑暗和光明之中直面自己的过去。"},{"id":240221,"p":"/4KbCbLpvs380nz0Az0pFrHwTUz6.jpg","b":"/eKT3nIoUN0hd1yTVTXHKZ5ivPNI.jpg","t":"Koose Munisamy Veerappan","r":8.5,"y":2023,"rd":"2023-12-14","hs":1.625,"d":1.912,"mt":"tv","o":""},{"id":205434,"p":"/kC6CSCUQlb1MayCrtBqC1Rt0Ec7.jpg","b":"/qXio38JA0CSyIHBoEkr6iWknWMR.jpg","t":"印度连环杀手档案：德里屠夫","r":6,"y":2022,"rd":"2022-07-20","hs":1.445,"d":1.905,"mt":"tv","o":"德里监狱外出现多具被肢解的尸体和嘲讽性留言，警方因此开始追捕一名对体制心怀怨恨的老牌杀手。"},{"id":121119,"p":"/uhCl4MRhqgnBLyAAefkrVFA1xKu.jpg","b":"/5n7LCROcKgW4D1YTrBb5b4cTz6k.jpg","t":"Contract","r":6,"y":2021,"rd":"2021-03-18","hs":1.315,"d":1.889,"mt":"tv","o":""},{"id":133089,"p":"/bNELomN08aduocxuxcQtQ6JAS8i.jpg","b":"/jIsX9j0BZrN2VdZfKMlnqnK8gOu.jpg","t":"纳粹邪教在智利","r":6.6,"y":2021,"rd":"2021-10-01","hs":1.302,"d":1.859,"mt":"tv","o":"在富有魅力并善于操纵人心的领袖带领下，一群德国基督徒在智利发展壮大，成为了独裁统治的工具。"},{"id":78602,"p":"/ol6BurbIg7aj4HUf3Nll04a8VIu.jpg","b":"/hXCzcrEoQMH1Z53YJKc2CaNyqWx.jpg","t":"An American Murder Mystery: The Staircase","r":6.8,"y":2018,"rd":"2018-04-08","hs":1.062,"d":1.855,"mt":"tv","o":""},{"id":129317,"p":"/n5K0vtLRWaDHAOGtrOGVauzRLOS.jpg","b":"/61mNM2osh3w7XAB6slxpGEwqt37.jpg","t":"মরীচিকা","r":4,"y":2021,"rd":"2021-06-14","hs":1.297,"d":1.846,"mt":"tv","o":""},{"id":251100,"p":"/4oYlpZ24u0RvSLQK5hlNVcCM9Nm.jpg","b":"/d5fTd3S1IF2dfFByEfJWoXtflwL.jpg","t":"完美妻子：雪莉·帕皮尼的神秘失踪事件","r":8,"y":2024,"rd":"2024-06-20","hs":1.824,"d":1.823,"mt":"tv","o":""},{"id":237806,"p":"/sxvgfexaVKoLtDv5Jy2w3s97TsJ.jpg","b":"/3izzVh7Jq8ZJJ0vUr22VXFU3LpH.jpg","t":"致死方休：跨国情侣弑亲疑云","r":6.9,"y":2023,"rd":"2023-11-01","hs":1.546,"d":1.767,"mt":"tv","o":"1985年杀害女友父母的凶手是延斯·索林，还是其女友本人？这部系列纪录片深度探讨了该案至今仍未解开的谜题。"},{"id":41481,"p":"/r8BIIQ0DzyoYXGW3IuZbnXYtV3.jpg","b":"/acKSRp5nuUn3CgJkIFm2NUyH158.jpg","t":"案藏旧事","r":6.5,"y":2011,"rd":"2011-10-06","hs":0.772,"d":1.764,"mt":"tv","o":"该剧由Philip Glenister和Thekla Reuten领衔主演，Ronan Bennett编剧，是一部四集惊悚迷你剧。当一位神秘的律师Gina出现，要求Harry为她的客户寻找一位失踪的时间证人。Harry接下了这份工作，但却不知不觉卷入了20年前哥哥死因的调查，他很快发现自己陷入了一个复杂的阴谋里。"},{"id":214619,"p":"/4bcVytWyujYnwtRtynLE0ouAgh0.jpg","b":"/drV1OiEsv9JsyL5GZFp0CjtwJsI.jpg","t":"国王","r":8.4,"y":2022,"rd":"2022-11-16","hs":1.375,"d":1.748,"mt":"tv","o":"这是一部关于吉米·赞博（Jimmy Zámbó）生平的十集系列片，展现了这位充满冲突的传奇歌手成名的过程。它还将带我们回到过去，了解共产主义的终结对匈牙利音乐界的影响。"},{"id":114809,"p":"/nXgDr8WmsTRkzHvAKqYuLN991lS.jpg","b":"/lHU8nbC37TTajXD9A1vtm1ZPdy9.jpg","t":"তাকদীর","r":7.9,"y":2020,"rd":"2020-12-18","hs":1.149,"d":1.714,"mt":"tv","o":""},{"id":291433,"p":"/cEE9AhQ6o4iyFYJPaG8SUVH9O20.jpg","b":"/IjELjhQpJ3aaINjnWLWrLQc0jE.jpg","t":"绝境：是非高地","r":7,"y":2022,"rd":"2022-09-08","hs":1.343,"d":1.687,"mt":"tv","o":"在《绝境》的这部续集中，一名邪教成员被谋杀，而此案与摩托车帮的土地纠纷和 2013 年的女子失踪案有关。安德里和亨莉卡对此展开调查。"},{"id":76277,"p":"/NMUaIdDYZFOg1XAWES7Zg1ZIXK.jpg","b":"/jH3rRtfUAmAxiAxZaQYuysz05gf.jpg","t":"姬芮","r":6.2,"y":2018,"rd":"2018-01-10","hs":0.974,"d":1.623,"mt":"tv","o":"　　《国家淫才 National Treasure》第二季，副标题《姬芮 Kiri》的4集新季讲述一个即将被白人家庭领养的黑人女孩被绑架后而遭受的谎言、责备和恶名。"},{"id":87415,"p":"/pah40fuJA2tZBcY1rhvpSlj0Ys1.jpg","b":"/3PKQxHD3PK23IRAL79Ww3zY0gbt.jpg","t":"暗影行者","r":6,"y":2019,"rd":"2019-03-08","hs":1.032,"d":1.617,"mt":"tv","o":"　　一个前警察拥有不会感受到痛楚的特殊能力，无法走出痛失至亲的他，开始独自追捕躲过警方的犯人！"},{"id":106666,"p":"/j03qsJwmTLyqfNhWiDgnxGKPABE.jpg","b":"/qXPY1M5qZcPbS8UFZVIe6S4tqUs.jpg","t":"Knutby: I blind tro","r":6.267,"y":2021,"rd":"2021-04-04","hs":1.181,"d":1.595,"mt":"tv","o":""},{"id":112278,"p":"/oODwXKC36RkIbdstNeOFyKm4MOK.jpg","b":"/sWARKmsxtkTbYzALlg0Rqt0hcUb.jpg","t":"第四次审判","r":6.8,"y":2020,"rd":"2020-11-11","hs":1.074,"d":1.55,"mt":"tv","o":"1993 年波士顿一起杀警案，让当时还是青少年的尚恩·艾利斯被控有罪，此后他奋力证明自己的清白，同时揭发警界的贪污腐败和体制中的种族歧视。"},{"id":261034,"p":"/tgG5s8U5Gd7jzVsCsTs4ejtnM4c.jpg","b":"/2o4l6890XYwIRuT4GCpp4zL7jsq.jpg","t":"美国谋杀故事：杀妻疑云","r":7.2,"y":2024,"rd":"2024-08-14","hs":1.6,"d":1.487,"mt":"tv","o":"拉西·彼得森失踪时已怀有八个月身孕。人们展开搜寻，结果却以悲剧告终。这部系列纪录片对这起 2002 年的谋杀案进行了深入探究。"},{"id":205845,"p":"/si5X3UeJNiwQKkR5iV4pWpn5szy.jpg","b":"/ev1oobREFwmurQep48TJF7uH3ZB.jpg","t":"Syndicate","r":8,"y":2022,"rd":"2022-07-10","hs":1.233,"d":1.476,"mt":"tv","o":""},{"id":253485,"p":"/16xXQNto7C0xQLYHXkfqlMK4kI8.jpg","b":"/cffJPnQFqvh2WjPAxztmAWr1G6i.jpg","t":"嗜血大廚的自白","r":6.7,"y":2024,"rd":"2024-05-10","hs":1.582,"d":1.464,"mt":"tv","o":"本紀錄片系列剖析一樁兇殺案，涉案的西班牙大廚透過巧妙編造的祕密與假身分，打造出備受矚目的亮眼職涯。"},{"id":233722,"p":"/fmExPTymtroHmc5hEaKvi6PQIE3.jpg","b":"/1UB7qOEjGV3Ei9E8HOSAS7eEqmo.jpg","t":"英国新闻之花枪杀案","r":6.6,"y":2023,"rd":"2023-09-26","hs":1.368,"d":1.463,"mt":"tv","o":"这部深度记录片回顾了 1999 年备受喜爱的电视节目主持人吉尔·丹多遭到谋杀的惊人案件，此案至今仍令专家和公众感到困惑。"},{"id":283622,"p":"/noKpRes8qwGlpXCHzFbZ9VUTNqq.jpg","b":"/mo6SlYqLG7yyDQXUEaY20TH8oLf.jpg","t":"Kobali","r":7,"y":2025,"rd":"2025-02-04","hs":1.934,"d":1.46,"mt":"tv","o":""},{"id":215117,"p":"/t0hkS7QNAUmhqPqgUu0tUsCL1c0.jpg","b":"/pyQyNIp4kGOcIfMfMxUi10uCu6u.jpg","t":"别接电话：脱衣搜身欺诈案","r":6.5,"y":2022,"rd":"2022-10-25","hs":1.212,"d":1.442,"mt":"tv","o":"有人通过欺诈电话说服美国各地快餐店的经理对员工进行脱衣搜身。这部纪录片剧集围绕针对此人的调查展开。"},{"id":66201,"p":"/339w1FvyQvZTdaY6knV4iaItRJJ.jpg","b":"/sqQmWvMePtfggAmFBiaA6oqltXi.jpg","t":"晦暗真相","r":7.9,"y":2016,"rd":"2016-03-27","hs":0.809,"d":1.414,"mt":"tv","o":"本系列纪录片深入探讨2006年一起爆炸性的13岁以色列女童谋杀案，以及一名乌克兰移民遭定罪的后续事件。"}]