[{"id":257932,"p":"/g2w3C3qap1btgCvFOJiYki4aNmy.jpg","b":"/6i29AyCu1aKAbzbmQITTmOF2cVb.jpg","t":"龙之谷：破晓奇兵","r":7.594,"y":2014,"rd":"2014-05-20","hs":1.155,"d":2.896,"mt":"anime","o":"不务正业的流浪少年兰伯特意外听到了邪恶的大黑龙手下魔族准备攻占阿尔特里亚大陆的情况，为了保护家乡他与魔物周旋被困，却被游侠巴尔纳救下，加入到了游侠杰兰特、阿尔杰塔（景甜 配音）的队伍中。精灵一族中的法师首领卡拉秋（夏梓桐 配音）也带着公主内尔文与弓箭手随从莉亚（徐娇 配音）前来邀请人类国王参战，面对魔物的入侵，他们和游侠队伍以及人类骑士贝斯柯德（胡歌 配音）组成了对付大黑龙的联盟。众人历经困难来到了大黑龙的巢穴，兰伯特与莉亚日久生情，但是他们却不知道杰兰特和阿尔杰塔，以及贝斯柯德各自带着不为人知的秘密……"},{"id":523777,"p":"/l9Xx3CfymHwat8MUkxRu2DEpAU.jpg","b":"/kkvejdQGeRH03ASrIKVqlFQMDeG.jpg","t":"未來世代","r":7,"y":2018,"rd":"2018-09-07","hs":1.129,"d":2.051,"mt":"anime","o":"孤獨的小麥與一名絕密機器人培養出看似不可能的情誼後，他倆展開一場動作緊湊的刺激冒險，著手瓦解一名邪惡壞蛋的陰謀。  這部爆炸性的動畫驚悚片，改編自王尼瑪的漫畫作品《7723》。"},{"id":333667,"p":"/3L5LhcYOp4MMyResaX2kOtVHNN8.jpg","b":"/vHiTIgoIoF1rjnjeC4n3qYaZ7Ua.jpg","t":"摇滚藏獒","r":6.172,"y":2016,"rd":"2016-07-08","hs":0.762,"d":1.343,"mt":"anime","o":"藏獒波弟（郭麒麟 配音）在山村长大，本该子承父业担当村庄卫士，却爱上了现代摇滚乐。为了追求音乐梦想，他进入城市，寻找乐队未果、拜师学艺受挫、屡遭狼群算计，但他坚持不懈，不仅拯救村民，还弥补了亲情上的裂痕，最终梦想成真。"}]